{
  "version": 2,
  "built_at": "2026-06-20T10:24:28+09:00",
  "page": 6,
  "page_size": 20,
  "count": 20,
  "items": [
    {
      "collected_at": "2026-06-18T06:13:57+09:00",
      "country": "US",
      "country_ko": "미국",
      "id": "c4c14ad929f0",
      "image_url": "https://media.newscentermaine.com/assets/WCSH/images/271844ac-4031-45ee-b1b3-f616b6a3d433/271844ac-4031-45ee-b1b3-f616b6a3d433_1140x641.jpg",
      "lang_original": "en",
      "lat": 44.4042,
      "lon": -70.7906,
      "processed_at": "2026-06-19T12:55:41+09:00",
      "raw_excerpt": "The Maine Mineral and Gem Museum in Bethel honored Neil Armstrong's first steps on the moon on July 20, 1969 with an unveiling of new artifacts.",
      "region": "Bethel, Maine",
      "source_name": "newscentermaine.com",
      "source_type": "google",
      "source_url": "https://www.newscentermaine.com/article/news/local/maine-museum-unveils-largest-piece-of-moon-to-fall-on-the-planet/97-048119a7-f877-4253-8e8a-68356760f630",
      "summary_en": "The Maine Mineral and Gem Museum in Bethel showed new space artifacts. The display honored Neil Armstrong's first steps on the Moon on July 20, 1969.",
      "summary_ko": "메인주 베설의 메인 광물·보석 박물관이 새 우주 유물을 공개했다. 이번 전시는 1969년 7월 20일 닐 암스트롱이 달에 첫발을 디딘 일을 기념했다.",
      "title_en": "Maine museum shows a large Moon rock",
      "title_ko": "메인주의 박물관이 큰 달 운석을 공개하다",
      "title_original": "Maine museum unveils largest piece of Moon to fall on the planet - newscentermaine.com",
      "triviality_score": 5
    },
    {
      "collected_at": "2026-06-18T08:14:02+09:00",
      "country": "CA",
      "country_ko": "캐나다",
      "fallback_reason": "",
      "id": "f25e291cf1d7",
      "image_url": "https://journalsaint-francois.ca/wp-content/uploads/sites/6/2025/10/1759721205_GL-03052016-CVHS-plan.jpg",
      "lang_original": "en",
      "lat": null,
      "lon": null,
      "processed_at": "2026-06-19T14:18:06+09:00",
      "provider_used": "opencode",
      "raw_excerpt": "This year, the Chateauguay Valley Historical Society hopes to honour the community’s rich history in the form of a museum. Since its inception over 50 years ago, the Chateauguay Valley Historical Society has aimed to open a museum. Over the years, many obstacles have delayed the project—in fact, the mission…",
      "region": "Quebec",
      "source_name": "Le journal Saint-François",
      "source_type": "google",
      "source_url": "https://journalsaint-francois.ca/chateauguay-valley-historical-society-exploring-the-possibility-of-opening-a-local-museum/",
      "summary_en": "The Chateauguay Valley Historical Society has spent over 50 years trying to open a local museum. The group is now exploring the possibility again after many obstacles delayed the project. The museum would honor the community's rich history.",
      "summary_ko": "샤토게 계곡 역사 협회가 50년 넘게 추진해 온 지역 박물관 개관 계획이 다시 추진력을 얻고 있다. 여러 장애물로 계속 미뤄졌지만, 협회는 지역 사회의 풍부한 역사를 기릴 박물관 건립 가능성을 다시 타진 중이다.",
      "title_en": "Quebec Historical Society Revives Museum Plan After 50 Years",
      "title_ko": "50년 만에 다시 추진되는 퀘벡 지역 역사 박물관",
      "title_original": "Chateauguay Valley Historical Society Exploring the Possibility of Opening a Local Museum - Le journal Saint-François",
      "triviality_score": 4
    },
    {
      "collected_at": "2026-06-17T20:10:45+09:00",
      "country": "AR",
      "country_ko": "아르헨티나",
      "id": "d365990effb1",
      "image_url": "https://www.argentina.gob.ar/sites/default/files/2025/07/whatsapp_image_2025-07-28_at_15.40.12_1.jpeg",
      "lang_original": "es",
      "lat": null,
      "lon": null,
      "processed_at": "2026-06-17T22:21:00+09:00",
      "raw_excerpt": "Son pueblos que resguardan vestigios de un pasado que marcó su identidad y que manifiestan un compromiso con la cultura local y el desarrollo del turismo rural.",
      "region": null,
      "source_name": "Argentina.gob.ar",
      "source_type": "google",
      "source_url": "https://www.argentina.gob.ar/noticias/tres-destinos-en-argentina-para-conocer-circuitos-mineros-historicos",
      "summary_en": "Argentina highlights three places where visitors can learn about historic mining routes. The places keep traces of the past and support local culture and rural tourism.",
      "summary_ko": "아르헨티나가 역사적인 광산 탐방로를 둘러볼 수 있는 세 곳을 소개했다. 이 마을들은 지역의 정체성을 만든 과거의 흔적을 간직하며, 지역 문화와 농촌 관광을 함께 살리고 있다.",
      "title_en": "Three Argentine Places to Visit Old Mining Routes",
      "title_ko": "아르헨티나의 옛 광산길을 만나는 세 여행지",
      "title_original": "Tres destinos en Argentina para conocer circuitos mineros históricos - Argentina.gob.ar",
      "triviality_score": 4
    },
    {
      "collected_at": "2026-06-17T22:08:45+09:00",
      "country": "ES",
      "country_ko": "스페인",
      "id": "0ac00b1186fd",
      "image_url": "https://static.eldiario.es/clip/78df1669-15a8-4645-9716-55c179e4f897_facebook-watermarked-aspect-ratio-1200-675_default_0.jpg",
      "lang_original": "es",
      "lat": 39.4699,
      "lon": -0.3763,
      "processed_at": "2026-06-18T00:21:44+09:00",
      "raw_excerpt": "El Año Sorolla refuerza la complicidad del Estado con Madrid, que en 2022 invirtió medio millón de euros en adquirir seis pinturas para el Museo Sorolla, que muestra 114 obras del valenciano y conserva 1.500 en sus almacenes",
      "region": "Valencia",
      "source_name": "elDiario.es",
      "source_type": "google",
      "source_url": "https://www.eldiario.es/cultura/arte/cultura-no-compra-obra-sorolla-museo-bellas-artes-valencia-40-anos_1_9937525.html",
      "summary_en": "Spain's culture ministry has not bought a Sorolla artwork for the Museum of Fine Arts of Valencia for almost 40 years. The report compares this with recent state support for Madrid's Sorolla Museum, which received six paintings in 2022.",
      "summary_ko": "스페인 문화부는 거의 40년 동안 발렌시아 미술관을 위해 소로야 작품을 사지 않았다. 기사에서는 2022년 마드리드 소로야 미술관에 작품 여섯 점을 사 준 국가 지원과 비교하고 있다.",
      "title_en": "Spain Has Not Bought Sorolla Works for Valencia Museum in Decades",
      "title_ko": "스페인, 발렌시아 미술관에 소로야 작품 40년 가까이 미구입",
      "title_original": "Cultura no compra obra de Sorolla al Museo de Bellas Artes de Valencia desde hace casi 40 años - elDiario.es",
      "triviality_score": 3
    },
    {
      "collected_at": "2026-06-18T02:13:33+09:00",
      "country": "NL",
      "country_ko": "네덜란드",
      "id": "8f980698d414",
      "image_url": "https://www.worldatlas.com/r/w1200-q80/upload/91/d3/02/shutterstock-1331924705-s3cdn.jpg",
      "lang_original": "en",
      "lat": null,
      "lon": null,
      "processed_at": "2026-06-18T12:20:38+09:00",
      "raw_excerpt": "These eight Dutch towns pair memorable main streets with canals, churches, shops, and museums that give each stop a distinct sense of place.",
      "region": null,
      "source_name": "WorldAtlas",
      "source_type": "google",
      "source_url": "https://www.worldatlas.com/cities/8-netherlands-towns-with-unforgettable-main-streets.html",
      "summary_en": "Eight towns in the Netherlands have main streets that stand out. The streets are linked with canals, churches, shops, and museums that give each town its own feel.",
      "summary_ko": "네덜란드의 여덟 마을에는 인상적인 중심가가 있다. 운하, 교회, 상점, 박물관이 어우러져 각 마을만의 분위기를 만든다.",
      "title_en": "Eight Dutch Towns With Memorable Main Streets",
      "title_ko": "기억에 남는 중심가가 있는 네덜란드 마을 8곳",
      "title_original": "8 Netherlands Towns With Unforgettable Main Streets - WorldAtlas",
      "triviality_score": 4
    },
    {
      "collected_at": "2026-06-18T00:12:39+09:00",
      "country": "JP",
      "country_ko": "일본",
      "id": "753e697ac6eb",
      "image_url": "https://cdn.image.st-hatena.com/image/scale/39fab7d409d0c19f7a8f17bcb713617e6247b68a/backend=imagemagick;version=1;width=1300/https%3A%2F%2Fcdn-ak.f.st-hatena.com%2Fimages%2Ffotolife%2Fc%2Fcolorful-company-kanazawa%2F20250922%2F20250922112950.jpg",
      "lang_original": "ja",
      "lat": 37.12,
      "lon": 137.0,
      "processed_at": "2026-06-18T06:20:21+09:00",
      "raw_excerpt": "10月12日・13日の2日間、能登島家族旅行村Weランドにて「能登島キャンパーズミーティング2025」を開催！ アウトドア体験と地域の魅力が融合した、家族や仲間みんなで楽しめるキャンプイベントが今年もやってきました♡ さまざまなキャンプスタイルの人達が交流することにより、より楽しいキャンプになること、アウトドアの魅力をより多くの人に発信することを目的に、2023年に誕生した地域密着型のアウトドアフェスティバル「能登島キャンパーズミーティング2025」。 今年のテーマは、お米（こめ）。 震災の影響で米作りを断念する農家も出る中、あらためて「能登島の米」に光を当て、自然豊かなフィールドを活かして「…",
      "region": "Nanao, Ishikawa",
      "source_name": "weekend-kanazawa.com",
      "source_type": "google",
      "source_url": "https://www.weekend-kanazawa.com/entry/notojimacamp",
      "summary_en": "A family camping event will be held at Notojima Family Travel Village We Land in Nanao on October 12 and 13. The 2025 theme is rice, and the event highlights Notojima rice after some farmers gave up rice growing because of the earthquake.",
      "summary_ko": "나나오의 노토지마 가족여행촌 위랜드에서 10월 12일과 13일 가족 캠핑 행사가 열린다. 올해 주제는 쌀이며, 지진 여파로 벼농사를 포기한 농가가 나온 뒤 노토지마 쌀의 가치를 다시 알리는 행사다.",
      "title_en": "Notojima camping festival will spotlight local rice",
      "title_ko": "노토지마 캠핑 축제, 지역 쌀을 조명",
      "title_original": "10/12（土）・13（月・祝）家族で楽しめるアウトドア体験満載！「能登島キャンパーズミーティング2025」が能登島家族旅行村Weランドにて開催♪【七尾・イベント】 - weekend-kanazawa.com",
      "triviality_score": 5
    },
    {
      "collected_at": "2026-06-17T08:55:44+09:00",
      "country": "US",
      "country_ko": "미국",
      "id": "53dbe2e93fe5",
      "image_url": "https://gray-wcax-prod.gtv-cdn.com/resizer/v2/ZV24QXUKQFGG3HJU2AJSOE5NZQ.jpg?auth=f65a2feac51181d9fc7cba15dfd0822d10b53c2b5b45f633bfb996be29130ac4&width=1200&height=600&smart=true",
      "lang_original": "en",
      "lat": 43.1726,
      "lon": -72.6079,
      "processed_at": "2026-06-17T15:43:49+09:00",
      "raw_excerpt": "One of Vermont's most historic cheesemakers got a chance to continue its legacy by teaming up with another to bring its cheese into the future.",
      "region": "Grafton, Vermont",
      "source_name": "WCAX",
      "source_type": "google",
      "source_url": "https://www.wcax.com/2026/05/25/made-vermont-grafton-village-cheese/",
      "summary_en": "Grafton Village Cheese, a historic Vermont cheesemaker, is working with another cheesemaker to keep its legacy alive. The partnership aims to help bring its cheese into the future.",
      "summary_ko": "버몬트의 오래된 치즈 공방인 그래프턴 빌리지 치즈가 전통을 이어 가기 위해 다른 치즈 업체와 손잡았다. 이번 협력은 이 치즈를 앞으로도 계속 이어 가기 위한 움직임이다.",
      "title_en": "Historic Vermont Cheesemaker Plans Its Next Chapter",
      "title_ko": "버몬트의 오래된 치즈 공방, 새 파트너와 다음 길을 찾다",
      "title_original": "Made in Vermont: Grafton Village Cheese - WCAX",
      "triviality_score": 5
    },
    {
      "collected_at": "2026-06-19T22:02:07+09:00",
      "country": "NO",
      "country_ko": "노르웨이",
      "fallback_reason": "",
      "id": "14eccfc83518",
      "image_url": "https://assets.thelocal.com/cdn-cgi/rs:fit:1200/quality:75/plain/https://apiwp.thelocal.com/wp-content/uploads/2023/04/watermarks-logo-Naked-man-Marvin-Meyer-Unsplash.jpg@webp",
      "lang_original": "en",
      "lat": null,
      "lon": null,
      "processed_at": "2026-06-20T06:22:07+09:00",
      "provider_used": "opencode",
      "raw_excerpt": "While Scandinavian countries are known for traditionally being comfortable with nakedness, Norwegians – especially younger generations – are not big on public nudity. However, there is a time and place for getting naked in public.",
      "region": null,
      "source_name": "The Local Norway",
      "source_type": "rss",
      "source_url": "https://www.thelocal.no/20230404/how-where-and-when-can-you-get-naked-in-norway",
      "summary_en": "Younger Norwegians are more reserved about public nudity than older generations. But there are still accepted times and places to be naked in public in Norway.",
      "summary_ko": "젊은 노르웨이인들은 나체에 대해 예전 세대보다 더 보수적입니다. 그래도 노르웨이에는 공공장소에서 옷을 벗어도 괜찮은 때와 장소가 있습니다.",
      "title_en": "The naked truth: When and where can you get naked in Norway?",
      "title_ko": "노르웨이에서 알몸으로 있어도 되는 때와 장소",
      "title_original": "How, where and when can you get naked in Norway?",
      "triviality_score": 4
    },
    {
      "collected_at": "2026-06-20T00:09:09+09:00",
      "country": "US",
      "country_ko": "미국",
      "fallback_reason": "",
      "id": "6a902e1a32b1",
      "image_url": "https://npr.brightspotcdn.com/dims4/default/ef32cec/2147483647/strip/true/crop/3024x1588+0+1167/resize/1200x630!/quality/90/?url=http%3A%2F%2Fnpr-brightspot.s3.amazonaws.com%2F47%2F47%2Fc246cf33444d963fae4399768fb5%2Fhood-alisa-swindell-aifg.jpg",
      "lang_original": "en",
      "lat": 44.0,
      "lon": -72.5,
      "processed_at": "2026-06-20T10:16:11+09:00",
      "provider_used": "opencode",
      "raw_excerpt": "Curators at local museums and art centers share details of soon-to-open exhibitions and events.",
      "region": "Vermont",
      "source_name": "Vermont Public",
      "source_type": "google",
      "source_url": "https://www.vermontpublic.org/show/vermont-edition/2024-01-17/beat-the-winter-blues-with-these-upcoming-vermont-art-exhibits",
      "summary_en": "Curators at local Vermont museums and art centers share details of soon-to-open exhibitions. These events offer a great indoor activity during the cold winter months. Many shows highlight local artists and community stories.",
      "summary_ko": "버몬트 지역 박물관과 미술관 큐레이터들이 곧 시작될 전시회와 행사 정보를 소개한다. 추운 겨울 실내에서 즐기기 좋은 이 전시들은 지역 작가와 커뮤니티 이야기를 중심으로 구성된다.",
      "title_en": "Upcoming Vermont art exhibits to beat winter blues",
      "title_ko": "겨울을 즐겁게 보낼 버몬트 지역 미술 전시회",
      "title_original": "Beat the winter blues with these upcoming Vermont art exhibitions - Vermont Public",
      "triviality_score": 4
    },
    {
      "collected_at": "2026-06-19T22:02:00+09:00",
      "country": "FR",
      "country_ko": "프랑스",
      "fallback_reason": "",
      "id": "c9ac6246c26a",
      "image_url": "https://assets.thelocal.com/cdn-cgi/rs:fit:1200/quality:75/plain/https://apiwp.thelocal.com/wp-content/uploads/2026/06/watermarks-logo-adam-word-of-day.jpg@webp",
      "lang_original": "en",
      "lat": null,
      "lon": null,
      "processed_at": "2026-06-20T06:21:47+09:00",
      "provider_used": "opencode",
      "raw_excerpt": "You might be considering this as the temperature soars.",
      "region": null,
      "source_name": "The Local France",
      "source_type": "rss",
      "source_url": "https://www.thelocal.fr/20260619/french-phrase-of-the-day-tenue-dadam",
      "summary_en": "Tenue d'Adam literally means \"Adam's outfit\" in French. It humorously refers to wearing no clothes at all on hot summer days. This lighthearted expression is perfect when the temperature soars.",
      "summary_ko": "Tenue d'Adam은 프랑스어로 직역하면 '아담의 의상'이라는 뜻이다. 더운 여름날 아무것도 입지 않은 상태를 재치 있게 가리키는 표현이다. 무더위가 계속될 때 가볍게 쓸 수 있는 유쾌한 표현이다.",
      "title_en": "French Phrase of the Day: Tenue d'Adam",
      "title_ko": "오늘의 프랑스어 표현: Tenue d'Adam",
      "title_original": "French Phrase of the Day: Tenue d'Adam",
      "triviality_score": 5
    },
    {
      "collected_at": "2026-06-19T22:01:56+09:00",
      "country": "SE",
      "country_ko": "스웨덴",
      "fallback_reason": "",
      "id": "0b23f1e70f1d",
      "image_url": "https://assets.thelocal.com/cdn-cgi/rs:fit:1200/quality:75/plain/https://apiwp.thelocal.com/wp-content/uploads/2021/06/watermarks-logo-sdluwPzT-TmIg4-nh-1.jpg@webp",
      "lang_original": "en",
      "lat": 59.3293,
      "lon": 18.0686,
      "processed_at": "2026-06-20T06:21:24+09:00",
      "provider_used": "opencode",
      "raw_excerpt": "The Local spoke to Eva Lenneman, a curator at Stockholm's Museum of Spirits in Stockholm about the history of snaps in Sweden.",
      "region": "Stockholm",
      "source_name": "The Local Sweden",
      "source_type": "rss",
      "source_url": "https://www.thelocal.se/20210624/why-do-swedes-drink-snaps-at-midsummer",
      "summary_en": "A museum curator explains why Swedes drink snaps at Midsummer. The tradition is closely tied to Swedish history and celebration culture.",
      "summary_ko": "스웨덴 한여름 축제에서 빠질 수 없는 술 스냅스의 역사를 박물관 큐레이터가 설명한다. 이 전통은 스웨덴의 축제 문화와 깊이 연결되어 있다.",
      "title_en": "How snaps became a Swedish Midsummer tradition",
      "title_ko": "스웨덴 한여름 축제에 스냅스가 빠지지 않는 이유",
      "title_original": "How did the drink Snaps come to define Swedish Midsummer?",
      "triviality_score": 4
    },
    {
      "collected_at": "2026-06-19T14:01:35+09:00",
      "country": "AU",
      "country_ko": "호주",
      "fallback_reason": "",
      "id": "b32c36cc2859",
      "image_url": "https://live-production.wcms.abc-cdn.net.au/d22cf20aa7a5b382e4d86f58d8d5bd93?impolicy=wcms_watermark_news&cropH=2809&cropW=4994&xPos=0&yPos=0&width=862&height=485&imformat=generic",
      "lang_original": "en",
      "lat": -34.9285,
      "lon": 138.6007,
      "processed_at": "2026-06-20T00:17:14+09:00",
      "provider_used": "opencode",
      "raw_excerpt": "SkyCity Adelaide reaches a settlement agreement with South Australia's Liquor and Gambling Commissioner in what the premier says is possibly the biggest fine handed out in the state's history.",
      "region": "South Australia",
      "source_name": "ABC Australia News",
      "source_type": "rss",
      "source_url": "https://www.abc.net.au/news/2026-06-19/skycity-adelaide-casino-fined-21-million/106817874",
      "summary_en": "SkyCity Adelaide reached a settlement with South Australia's gambling regulator. The premier says it is possibly the biggest fine in the state's history.",
      "summary_ko": "스카이시티 애들레이드가 사우스오스트레일리아 주 도박위원회와 합의에 도달했습니다. 주 총리는 이번 벌금이 주 역사상 가장 큰 규모일 수 있다고 밝혔습니다.",
      "title_en": "Adelaide casino operator fined $21m for failings",
      "title_ko": "애들레이드 카지노 업체, 2100만 달러 벌금 부과",
      "title_original": "Adelaide casino operator fined $21m for 'completely unacceptable' failings",
      "triviality_score": 3
    },
    {
      "collected_at": "2026-06-17T18:02:40+09:00",
      "country": "FR",
      "country_ko": "프랑스",
      "id": "bf1b8c93040f",
      "image_url": "https://assets.thelocal.com/cdn-cgi/rs:fit:1200/quality:75/plain/https://apiwp.thelocal.com/wp-content/uploads/2026/06/watermarks-logo-AFP__20260528__B4BK4T3__v2__MidRes__FilesFranceParisHeatCentury.jpg@webp",
      "lang_original": "en",
      "lat": 48.8566,
      "lon": 2.3522,
      "processed_at": "2026-06-17T18:15:14+09:00",
      "raw_excerpt": "France braced for another heat wave on Wednesday, with Paris allowing swimming in one of its canals so residents could cope with the heat.",
      "region": "Paris",
      "source_name": "The Local France",
      "source_type": "rss",
      "source_url": "https://www.thelocal.fr/20260617/france-braces-for-heatwave-with-canal-swimming-allowed-in-paris",
      "summary_en": "France prepared for another heat wave on Wednesday. Paris allowed swimming in one of its canals so residents could cool down.",
      "summary_ko": "프랑스는 수요일 또 한 번의 폭염에 대비했다. 파리는 주민들이 더위를 식힐 수 있도록 시내 운하 한 곳에서 수영을 허용했다.",
      "title_en": "Paris Opens Canal Swimming During Heat Wave",
      "title_ko": "폭염 속 파리, 운하 수영 허용",
      "title_original": "France braces for heatwave with canal swimming allowed in Paris",
      "triviality_score": 3
    },
    {
      "collected_at": "2026-06-17T22:12:09+09:00",
      "country": "IT",
      "country_ko": "이탈리아",
      "id": "9c4ccd91f325",
      "image_url": "https://images2-corrieredibologna.corriereobjects.it/methode_image/socialshare/2022/10/23/a7d525de-52e2-11ed-88b8-a93b9c4fff69.jpg",
      "lang_original": "it",
      "lat": 44.887,
      "lon": 11.415,
      "processed_at": "2026-06-18T02:18:25+09:00",
      "raw_excerpt": "La storia di marco Botti: «Cercavo i resti di uno sciame meteorico, ma sono saltate fuori altre cose». Il materiale consegnato al museo",
      "region": "Bondeno, Emilia-Romagna",
      "source_name": "Corriere di Bologna",
      "source_type": "google",
      "source_url": "https://corrieredibologna.corriere.it/bologna/cronaca/22_ottobre_23/bondeno-appassionato-astronomia-va-caccia-meteoriti-trova-monete-antiche-76e083ec-52e2-11ed-88b8-a93b9c4fff69.shtml",
      "summary_en": "In Bondeno, astronomy fan Marco Botti went looking for pieces of a meteor shower. Instead, he found ancient coins and gave the material to a museum.",
      "summary_ko": "이탈리아 본데노에서 천문 애호가 마르코 보티가 유성우의 흔적을 찾으러 나섰습니다. 그는 뜻밖에 고대 동전을 발견했고, 해당 자료를 박물관에 전달했습니다.",
      "title_en": "Meteorite Hunter Finds Ancient Coins",
      "title_ko": "운석 찾던 천문 애호가, 고대 동전을 발견하다",
      "title_original": "Bondeno, appassionato di astronomia va a caccia di meteoriti e trova monete antiche - Corriere di Bologna",
      "triviality_score": 5
    },
    {
      "collected_at": "2026-06-18T02:13:20+09:00",
      "country": "JP",
      "country_ko": "일본",
      "id": "47625a03cc3e",
      "image_url": "https://prcdn.freetls.fastly.net/release_image/58398/87/58398-87-7b8ec7e2c42fccc4493f4c599e1f87bd-3492x2329.jpg?format=jpeg&auto=webp&fit=bounds&width=2400&height=1260",
      "lang_original": "ja",
      "lat": 36.5613,
      "lon": 136.6562,
      "processed_at": "2026-06-18T12:19:02+09:00",
      "raw_excerpt": "ハイアット セントリック 金沢のプレスリリース（2025年10月6日 14時00分）ハイアット セントリック 金沢 | 金沢が誇る旬の味覚と地元生産者の思いを堪能「金沢産食材フェア ～ Kanazawa Storyディナー」",
      "region": "Kanazawa, Ishikawa",
      "source_name": "PR TIMES",
      "source_type": "google",
      "source_url": "https://prtimes.jp/main/html/rd/p/000000087.000058398.html",
      "summary_en": "Hyatt Centric Kanazawa announced a dinner fair using seasonal ingredients from Kanazawa. The event will share local flavors and the stories of local producers.",
      "summary_ko": "하얏트 센트릭 가나자와가 가나자와산 제철 식재료를 활용한 디너 행사를 알렸다. 이 행사는 지역의 맛과 생산자들의 이야기를 함께 전할 예정이다.",
      "title_en": "Kanazawa hotel plans local food dinner fair",
      "title_ko": "가나자와 호텔, 지역 식재료 디너 행사 연다",
      "title_original": "ハイアット セントリック 金沢 | 金沢が誇る旬の味覚と地元生産者の思いを堪能「金沢産食材フェア ～ Kanazawa Storyディナー」 - PR TIMES",
      "triviality_score": 3
    },
    {
      "collected_at": "2026-06-17T09:18:45+09:00",
      "country": "BR",
      "country_ko": "브라질",
      "id": "f5aa915574c3",
      "image_url": "https://www.bandab.com.br/wp-content/uploads/2026/06/rua-curitiba-bloqueios-boqueirao.jpg",
      "lang_original": "pt",
      "lat": -25.509,
      "lon": -49.239,
      "processed_at": "2026-06-17T15:58:25+09:00",
      "raw_excerpt": "Motoristas que circulam pelo bairro Boqueirão, em Curitiba, devem ficar atentos às mudanças no trânsito a partir desta quarta-feira (17). A Prefeitura de",
      "region": "Boqueirão, Curitiba, Paraná",
      "source_name": "Banda B",
      "source_type": "google",
      "source_url": "https://www.bandab.com.br/transito/rua-o-brasil-para-cristo-bloqueios-obras-boqueirao-curitiba/",
      "summary_en": "Drivers in Boqueirão, Curitiba, should watch for traffic changes from Wednesday, June 17. Work on an important local street will cause blocks and new routes.",
      "summary_ko": "쿠리치바 보케이라웅 지역을 지나는 운전자들은 6월 17일 수요일부터 교통 변경에 주의해야 합니다. 주요 지역 도로 공사로 일부 구간이 막히고 우회 동선이 생깁니다.",
      "title_en": "Road work changes traffic in Boqueirão",
      "title_ko": "보케이라웅 도로 공사로 교통 변경",
      "title_original": "Obra em importante rua do Boqueirão provoca bloqueios e muda trânsito a partir desta quarta-feira - Banda B",
      "triviality_score": 4
    },
    {
      "collected_at": "2026-06-17T14:06:16+09:00",
      "country": "NO",
      "country_ko": "노르웨이",
      "id": "da0b86d1baf7",
      "image_url": "https://www.arkitektur.no/media/22aaohp1/thumbnail_nora-headshots-24.jpg?rxy=0.44535879136914985,0.5189025031552921&width=1200&height=630&v=1dba7f97129ed30",
      "lang_original": "no",
      "lat": 59.9139,
      "lon": 10.7522,
      "processed_at": "2026-06-17T16:19:50+09:00",
      "raw_excerpt": "Vi tar Oslos særpreg for gitt, som noe som alltid vil være der, uansett hva som bygges. Snart våkner vi opp, ser ut av vinduet og vet ikke lenger hvor vi er.",
      "region": "Oslo",
      "source_name": "Arkitektur",
      "source_type": "google",
      "source_url": "https://www.arkitektur.no/meninger/debatt/vi-som-har-meninger-om-oslo-maa-innse-at-byen-ikke-er-et-stykke-isolert-rom/",
      "summary_en": "An architecture opinion piece says people take Oslo’s special character for granted. The writer warns that new building may slowly change the city until residents no longer feel they know where they are.",
      "summary_ko": "한 건축 의견 글은 사람들이 오슬로만의 개성을 당연하게 여긴다고 말한다. 글쓴이는 새 건물들이 도시를 서서히 바꾸어, 주민들이 더는 자신이 어디에 있는지 익숙하게 느끼지 못할 수 있다고 경고한다.",
      "title_en": "Oslo’s changing character worries architecture writer",
      "title_ko": "오슬로의 변하는 모습에 대한 건축계의 우려",
      "title_original": "– Vi som har meninger om Oslo, må innse at byen ikke er et stykke isolert rom - Arkitektur",
      "triviality_score": 3
    },
    {
      "collected_at": "2026-06-18T06:05:51+09:00",
      "country": "CH",
      "country_ko": "스위스",
      "id": "303cbb8d2cce",
      "image_url": "https://media.outnow.ch/News/2024/09/11/Das-ZFF-beginnt-beginnt-mit-einem-Knall-Jude-Law-bringt-gefeierten-Actionkracher-The-Order-zur-Eroef/teaser_lrg.jpg",
      "lang_original": "de",
      "lat": 47.3769,
      "lon": 8.5417,
      "processed_at": "2026-06-19T12:54:04+09:00",
      "raw_excerpt": "Am 3. Oktober beginnt das 20. Zurich Film Festival - und das mit einem Hollywoodstar! Der Brite Jude Law wird in die Limmatstadt reisen und den Film vom Justin Kurzel persönlich vorstellen.",
      "region": "Zurich",
      "source_name": "OutNow",
      "source_type": "google",
      "source_url": "https://outnow.ch/News/2024/09/11/Das-ZFF-beginnt-beginnt-mit-einem-Knall-Jude-Law-bringt-gefeierten-Actionkracher-The-Order-zur-Eroef",
      "summary_en": "The 20th Zurich Film Festival starts on October 3. British actor Jude Law will come to Zurich and present Justin Kurzel's film The Order in person.",
      "summary_ko": "제20회 취리히 영화제가 10월 3일 시작된다. 영국 배우 주드 로가 취리히를 찾아 저스틴 커젤 감독의 영화 The Order를 직접 소개한다.",
      "title_en": "Jude Law to Open Zurich Film Festival",
      "title_ko": "주드 로, 취리히 영화제 개막식 참석",
      "title_original": "Das ZFF beginnt mit einem Knall: Jude Law bringt gefeierten Actionkracher «The Order» zur Eröffnung - OutNow",
      "triviality_score": 3
    },
    {
      "collected_at": "2026-06-17T22:10:26+09:00",
      "country": "DE",
      "country_ko": "독일",
      "id": "df892ce9a4bd",
      "image_url": "https://www.freiepresse.de/DYNIMG/88/87/18218887_W2040C2040x1360o0x0.jpg",
      "lang_original": "de",
      "lat": null,
      "lon": null,
      "processed_at": "2026-06-18T02:14:06+09:00",
      "raw_excerpt": "Bei jüngsten Bohrungen in seiner Lagerstätte im Vogtland stößt die Freiberger Saxore Bergbau GmbH auf deutlich mehr Zinn als zuletzt erwartet. Und auf ein Metall, das bislang fast nur aus China kommt.",
      "region": "Vogtland, Saxony",
      "source_name": "Freie Presse",
      "source_type": "google",
      "source_url": "https://www.freiepresse.de/nachrichten/sachsen/rohstoffe-unter-diesem-dorf-im-vogtland-lauert-ein-milliardenschatz-nur-wann-wird-er-gehoben-artikel14134211",
      "summary_en": "A mining company found more tin than expected during recent drilling in Vogtland, Saxony. It also found another metal that has mostly come from China so far. The valuable deposit lies under a local village, but it is not clear when it will be mined.",
      "summary_ko": "작센주 포크틀란트에서 최근 시추를 하던 광산 회사가 예상보다 많은 주석을 확인했다. 지금까지 주로 중국에서 들여오던 또 다른 금속도 함께 발견됐다. 이 귀한 광물층은 한 마을 아래에 있지만, 언제 채굴될지는 아직 분명하지 않다.",
      "title_en": "Large tin find under a Vogtland village",
      "title_ko": "포크틀란트 마을 아래서 큰 주석 매장 확인",
      "title_original": "Wertvolle Rohstoffe: Unter diesem Dorf liegt ein Milliardenschatz - Freie Presse",
      "triviality_score": 3
    },
    {
      "collected_at": "2026-06-18T04:14:17+09:00",
      "country": "NO",
      "country_ko": "노르웨이",
      "id": "e6c705831b39",
      "image_url": "https://www.uib.no/sites/w3.uib.no/files/media/gittehansen.jpg",
      "lang_original": "no",
      "lat": 62.47,
      "lon": 6.2,
      "processed_at": "2026-06-18T14:18:48+09:00",
      "raw_excerpt": "\"Hva ble hentet inn til byen, hvordan produserte man varer og utviklet tilbud og hvordan ble dette forbrukt i den middelalderske byen Borgund utenfor Ålesund?\" Professor Gitte Hansen leder et stor arkeologisk og tverrfaglig forskningsprosjekt som skal gi nytt liv til gamle data ved å stille nye spørsmål og bruke nye metoder for å få nye svar på disse og andre spørsmål.",
      "region": "Sunnmøre",
      "source_name": "Universitetet i Bergen",
      "source_type": "google",
      "source_url": "https://www.uib.no/universitetsmuseet/165043/borgund-den-nedlagte-byen-på-sunnmøre",
      "summary_en": "Researchers at the University of Bergen are studying the old town of Borgund near Ålesund. They will use new methods to learn how goods came into the town, how things were made, and how people used them in the medieval city.",
      "summary_ko": "베르겐대학교 연구진이 올레순 근처의 옛 도시 보르군드를 연구하고 있다. 연구진은 새로운 방법으로 중세 도시 안에 물건이 어떻게 들어오고, 만들어지고, 소비됐는지 살펴볼 예정이다.",
      "title_en": "Old Borgund Town Gets New Questions",
      "title_ko": "사라진 보르군드 마을을 새롭게 살피다",
      "title_original": "Borgund - den nedlagte byen på Sunnmøre - Universitetet i Bergen",
      "triviality_score": 4
    }
  ]
}
