{
  "version": 2,
  "built_at": "2026-07-14T08:21:02+09:00",
  "page": 92,
  "page_size": 20,
  "count": 20,
  "items": [
    {
      "collected_at": "2026-07-03T16:02:05+09:00",
      "country": "NL",
      "country_ko": "네덜란드",
      "fallback_reason": "",
      "id": "eae501e4840f",
      "image_url": "https://www.dutchnews.nl/wpcms/wp-content/uploads/2026/07/Summer-heat-.jpg",
      "lang_original": "en",
      "lat": 52.1326,
      "lon": 5.2913,
      "processed_at": "2026-07-03T16:18:48+09:00",
      "provider_used": "opencode",
      "raw_excerpt": "The Netherlands is in for a dry and largely sunny weekend, with temperatures climbing to 27° or 28° in the southeast on Saturday, according to weather bureau Weeronline. Friday will be dry with sunny spells, and temperatures will reach 20° or 21° in the north and west and 22° to 24° elsewhere. On the beaches and the Wadden Islands it will be slightly cooler, at around 19°. Saturday will be the warmest day of the weekend. The south will see...",
      "region": null,
      "source_name": "DutchNews.nl",
      "source_type": "rss",
      "source_url": "https://www.dutchnews.nl/2026/07/sunny-dry-weekend-ahead-with-highs-of-up-to-28-in-southeast/",
      "summary_en": "The Netherlands will have a dry and sunny weekend with temperatures up to 28°C in the southeast on Saturday. Friday will also be dry with sunny spells and temperatures around 20-24°C. Coastal areas will be slightly cooler at about 19°C.",
      "summary_ko": "네덜란드는 이번 주말 건조하고 화창한 날씨가 예상되며, 토요일 남동부 지역은 기온이 28°C까지 오르겠다. 금요일도 건조하고 맑은 날씨로 기온은 20~24°C 수준이다. 해안가와 바덴 제도는 19°C로 약간 선선하겠다.",
      "title_en": "Sunny, dry weekend ahead with highs of up to 28° in southeast",
      "title_ko": "남동부 28도까지 오르는 맑고 건조한 주말",
      "title_original": "Sunny, dry weekend ahead with highs of up to 28° in southeast",
      "triviality_score": 4
    },
    {
      "collected_at": "2026-07-03T16:02:43+09:00",
      "country": "AU",
      "country_ko": "호주",
      "fallback_reason": "",
      "id": "9bea834ba6d3",
      "image_url": "https://npr.brightspotcdn.com/dims3/default/strip/false/crop/3529x1985+0+184/resize/1400/quality/85/format/jpeg/?url=http%3A%2F%2Fnpr-brightspot.s3.amazonaws.com%2F5d%2Fef%2Febc8660f4b568f6a6983b9173a46%2Fap26184091678068.jpg",
      "lang_original": "en",
      "lat": null,
      "lon": null,
      "processed_at": "2026-07-03T16:21:27+09:00",
      "provider_used": "opencode",
      "raw_excerpt": "The 5-year-old seal has a social media following twice the size of Tasmania's population, and his antics include bending traffic bollards and blocking roads.",
      "region": "Tasmania",
      "source_name": "NPR News",
      "source_type": "rss",
      "source_url": "https://www.npr.org/2026/07/03/g-s1-131911/australia-trouble-making-seal",
      "summary_en": "A 5-year-old seal named Neil has become a social media celebrity in Tasmania. His antics include bending traffic bollards and blocking roads. Officials are asking fans to give him space.",
      "summary_ko": "태즈메이니아의 5살짜리 물개 닐이 소셜 미디어 스타가 됐다. 교통 볼라드를 구부리거나 도로를 막는 장난으로 유명해졌다. 당국은 팬들에게 닐에게 거리를 둘 것을 당부했다.",
      "title_en": "Neil the seal's antics draw fans, worry officials in Australia",
      "title_ko": "말썽꾸러기 물개 닐, 팬들에게 인기지만 당국은 걱정",
      "title_original": "Australian officials ask fans to respect the privacy of Neil, a trouble-making seal",
      "triviality_score": 5
    },
    {
      "collected_at": "2026-07-03T16:02:44+09:00",
      "country": "IN",
      "country_ko": "인도",
      "fallback_reason": "",
      "id": "8fe62f13473a",
      "image_url": "https://th-i.thgim.com/public/news/national/andhra-pradesh/5uwalg/article71177627.ece/alternates/LANDSCAPE_1200/Lok.jpeg",
      "lang_original": "en",
      "lat": 16.43,
      "lon": 80.57,
      "processed_at": "2026-07-03T16:21:40+09:00",
      "provider_used": "opencode",
      "raw_excerpt": "IT Minister Nara Lokesh laid the foundation for ₹6.30-crore development works at the Sri Lakshmi Narasimha Swamy temple, including a new Yagasala.",
      "region": "Andhra Pradesh",
      "source_name": "The Hindu National",
      "source_type": "rss",
      "source_url": "https://www.thehindu.com/news/national/andhra-pradesh/lokesh-lays-foundation-for-630-crore-works-at-mangalagiri-sri-lakshmi-narasimha-swamy-temple/article71177480.ece",
      "summary_en": "IT Minister Nara Lokesh laid the foundation for new development works worth ₹6.30 crore at the Sri Lakshmi Narasimha Swamy temple in Mangalagiri. The project includes building a new Yagasala and other facilities.",
      "summary_ko": "IT 장관 나타 로케시가 망갈라기리 스리 락슈미 나라심하 스와미 사원에서 6.30크로르 규모의 개발 공사 기공식을 가졌다. 이 프로젝트에는 새 야가살라(제사 시설) 건립이 포함된다.",
      "title_en": "Minister Lokesh starts ₹6.30-crore temple development works in Mangalagiri",
      "title_ko": "로케시 장관, 망갈라기리 사원에 6.30크로르 개발 공사 기공",
      "title_original": "Lokesh lays foundation for ₹6.30-crore works at Mangalagiri Sri Lakshmi Narasimha Swamy temple",
      "triviality_score": 4
    },
    {
      "collected_at": "2026-07-03T16:03:24+09:00",
      "country": "IN",
      "country_ko": "인도",
      "fallback_reason": "",
      "id": "aaa8e34ea10e",
      "image_url": "https://th-i.thgim.com/public/incoming/5drsja/article71177626.ece/alternates/LANDSCAPE_1200/IMG_iStock-1406865705_2_1_ARBISUP1.jpg",
      "lang_original": "en",
      "lat": null,
      "lon": null,
      "processed_at": "2026-07-03T16:22:37+09:00",
      "provider_used": "opencode",
      "raw_excerpt": "Telangana government to declare 280 acres in Sardarnagar, Rangareddy district as Reserve Forest, enhancing land protection and conservation efforts.",
      "region": "Telangana",
      "source_name": "The Hindu National",
      "source_type": "rss",
      "source_url": "https://www.thehindu.com/news/national/telangana/280-acres-in-rangareddy-districts-sardarnagar-to-be-declared-reserve-forest/article71175456.ece",
      "summary_en": "The Telangana government will declare 280 acres in Sardarnagar, Rangareddy district as a Reserve Forest. This move strengthens land protection and conservation in the region.",
      "summary_ko": "텔랑가나 주정부가 랑가레디 지역 사르다르나가르의 280에이커를 보호림으로 지정한다. 이 조치는 해당 지역의 토지 보호와 환경 보전을 강화하기 위한 것이다.",
      "title_en": "280 acres in Rangareddy district's Sardarnagar to be declared reserve forest",
      "title_ko": "랑가레디 지역 사르다르나가르 280에이커, 보호림으로 지정 예정",
      "title_original": "280 acres in Rangareddy district’s Sardarnagar to be declared reserve forest",
      "triviality_score": 3
    },
    {
      "collected_at": "2026-07-03T16:04:00+09:00",
      "country": "FR",
      "country_ko": "프랑스",
      "fallback_reason": "",
      "id": "5f78c337ce36",
      "image_url": "https://assets.thelocal.com/cdn-cgi/rs:fit:1200/quality:75/plain/https://apiwp.thelocal.com/wp-content/uploads/2026/07/watermarks-logo-AFP__20260629__B8P78WE__v1__MidRes__FranceEnvironmentWeatherLeisure.jpg@webp",
      "lang_original": "en",
      "lat": 48.8566,
      "lon": 2.3522,
      "processed_at": "2026-07-03T16:22:58+09:00",
      "provider_used": "opencode",
      "raw_excerpt": "From Seine swimming to activities to do during heatwaves - this week’s La Belle Vie newsletter offers an insight into life in the big city under high temperatures.",
      "region": "Paris",
      "source_name": "The Local France",
      "source_type": "rss",
      "source_url": "https://www.thelocal.fr/20260702/la-belle-vie-biting-the-bullet-on-swimming-in-the-seine-and-july-activities-in-france",
      "summary_en": "A weekly newsletter shares tips for living in Paris during summer. It covers swimming in the Seine River and activities to beat the heatwave. This is a guide for everyday life in the big city.",
      "summary_ko": "파리 여름철 생활 팁을 전하는 주간 뉴스레터입니다. 센강에서 수영하는 법과 폭염을 이기는 액티비티를 소개합니다. 대도시에서의 일상을 위한 실용적인 가이드입니다.",
      "title_en": "Biting the bullet on swimming in the Seine and July activities in France",
      "title_ko": "센강 수영과 7월 파리 액티비티 가이드",
      "title_original": "La Belle Vie: Biting the bullet on swimming in the Seine and July activities in France",
      "triviality_score": 4
    },
    {
      "collected_at": "2026-07-03T16:13:53+09:00",
      "country": "BR",
      "country_ko": "브라질",
      "fallback_reason": "",
      "id": "c4e3cdd01f50",
      "image_url": "https://www.edmarlyra.com/wp-content/uploads/2026/07/IMG_0466.png",
      "lang_original": "pt",
      "lat": -8.0578,
      "lon": -34.8828,
      "processed_at": "2026-07-03T16:23:57+09:00",
      "provider_used": "opencode",
      "raw_excerpt": "Programa A Casa é Sua entrega – Mais 493 títulos de propriedade, dos quais 73% foram emitidos em nome de mulheres chefes de família. Prefeitura também firma acordos para beneficiar cerca de 2,3 mil famílias em outras comunidades e viabiliza novo conjunto habitacional no Pilar A Prefeitura do Recife deu mais um passo na maior […]",
      "region": "Recife, Pernambuco",
      "source_name": "Blog Edmar Lyra",
      "source_type": "google",
      "source_url": "https://www.edmarlyra.com/recife-regulariza-mais-1-117-imoveis-em-brasilia-teimosa-e-amplia-regularizacao-fundiaria/",
      "summary_en": "Recife city hall handed over 493 property titles, 73% of them to women who are heads of their households. The city also signed agreements to help about 2,300 families in other communities and approved a new housing project in Pilar.",
      "summary_ko": "헤시피 시청이 주택 소유권 증서 493건을 교부했고, 그중 73%는 여성 가장 명의로 발급됐다. 시는 다른 지역 약 2,300가구를 지원하는 협약도 체결하고 필라르 지역에 새 주택 단지를 승인했다.",
      "title_en": "Recife gives property titles to 1,117 homes in Brasilia Teimosa",
      "title_ko": "헤시피, 브라질리아 테이모자 지역 1,117채 주택 소유권 정리",
      "title_original": "Recife regulariza mais 1.117 imóveis em Brasília Teimosa e amplia regularização fundiária - Blog Edmar Lyra",
      "triviality_score": 4
    },
    {
      "collected_at": "2026-07-03T18:01:40+09:00",
      "country": "IT",
      "country_ko": "이탈리아",
      "fallback_reason": "",
      "id": "640bf0a87e3a",
      "image_url": "https://assets.thelocal.com/cdn-cgi/rs:fit:1200/quality:75/plain/https://apiwp.thelocal.com/wp-content/uploads/2026/05/watermarks-logo-andrea-mancini-0zl9Jq18gUk-unsplash.jpg@webp",
      "lang_original": "en",
      "lat": 40.0,
      "lon": 9.0,
      "processed_at": "2026-07-03T18:17:54+09:00",
      "provider_used": "opencode",
      "raw_excerpt": "Sardinia's beaches regularly appear in viral 'must-visit' rankings. But with heavy tourist pressure driving councils to bring in increasingly strict restrictions, those who actually get to experience Italy's 'top-rated' beaches may be limited.",
      "region": "Sardinia",
      "source_name": "The Local Italy",
      "source_type": "rss",
      "source_url": "https://www.thelocal.it/20260703/like-winning-the-lottery-italys-top-ranked-beaches-are-among-the-most-tightly-controlled",
      "summary_en": "Sardinia's beaches are praised in many online rankings. Heavy tourist pressure forces local councils to add strict rules. Visiting the top-rated beaches now feels like winning the lottery.",
      "summary_ko": "사르데냐의 해변들은 각종 온라인 순위에서 극찬을 받는다. 하지만 과도한 관광 수요 때문에 지역 지자체들이 점점 더 엄격한 제한을 도입하고 있다. 최고 평점을 받은 해변을 실제로 방문하는 것이 마치 로또에 당첨된 기분처럼 느껴질 정도다.",
      "title_en": "'Like winning the lottery': Italy's top-ranked beaches are among the most tightly controlled",
      "title_ko": "\"로또에 당첨된 기분\" — 관광객 통제 강화로 가기 어려워진 이탈리아 '최고의 해변들'",
      "title_original": "'Like winning the lottery': Italy's 'top-ranked' beaches are among the most tightly controlled",
      "triviality_score": 3
    },
    {
      "collected_at": "2026-07-03T18:01:44+09:00",
      "country": "NL",
      "country_ko": "네덜란드",
      "fallback_reason": "",
      "id": "688aa402ec5b",
      "image_url": "https://www.dutchnews.nl/wpcms/wp-content/uploads/2023/08/Depositphotos_91029386_S-e1783068319580.jpg",
      "lang_original": "en",
      "lat": null,
      "lon": null,
      "processed_at": "2026-07-03T18:18:07+09:00",
      "provider_used": "opencode",
      "raw_excerpt": "Three-quarters of the country took a summer holiday in 2025, according to research by the Dutch statistics office CBS. Figures from the CBS Holiday Survey show that, between April and October, 10.8 million people in the Netherlands took 21.9 million vacation days. Just over half of those days (12.9 million) were spent abroad, with the remaining 9 million days being enjoyed withing the Netherlands. France was the most popular, with the Dutch using 2.2 million days camping and eating baguettes,...",
      "region": null,
      "source_name": "DutchNews.nl",
      "source_type": "rss",
      "source_url": "https://www.dutchnews.nl/2026/07/france-tops-dutch-summer-holiday-destinations/",
      "summary_en": "Three-quarters of the Netherlands took a summer holiday in 2025. The Dutch spent 21.9 million vacation days, with over half abroad. France was the top destination with 2.2 million days.",
      "summary_ko": "2025년 네덜란드 국민 4분의 3이 여름휴가를 떠났다. 총 2190만 일의 휴가 중 절반 이상을 해외에서 보냈으며, 프랑스가 220만 일로 가장 인기 있는 목적지였다.",
      "title_en": "France tops Dutch summer holiday destinations",
      "title_ko": "네덜란드인 올해 여름휴가 1위 국가는 프랑스",
      "title_original": "France tops Dutch summer holiday destinations",
      "triviality_score": 3
    },
    {
      "collected_at": "2026-07-03T18:01:48+09:00",
      "country": "FI",
      "country_ko": "핀란드",
      "fallback_reason": "",
      "id": "a5bd0e98b7b3",
      "image_url": "https://img.img-cdn.yle.fi/crop_extract,w_6130,h_3441,x_0,y_128/crop_fill,w_1200,h_628/f_auto/39-16705556a467781aa7c1/1783003367",
      "lang_original": "en",
      "lat": 60.17,
      "lon": 24.94,
      "processed_at": "2026-07-03T18:18:54+09:00",
      "provider_used": "opencode",
      "raw_excerpt": "This is the largest litter born so far to Korkeasaari Zoo's \"little-known and elusive\" species of Central Asian grassland wildcat.",
      "region": "Uusimaa",
      "source_name": "YLE News",
      "source_type": "rss",
      "source_url": "https://yle.fi/a/74-20234726",
      "summary_en": "Korkeasaari Zoo in Helsinki has three new Pallas's cat kittens. This is the largest litter born at the zoo for this rare cat species. The Pallas's cat is a little-known wildcat from Central Asian grasslands.",
      "summary_ko": "헬싱키 코르케아사리 동물원에서 팔라스고양이 세 마리가 태어났다. 이 동물원에서 이 희귀한 고양이 종으로는 가장 많은 새끼가 태어난 기록이다. 팔라스고양이는 중앙아시아 초원이 원산지인 잘 알려지지 않은 야생 고양이다.",
      "title_en": "Pallas's cat gives birth to 3 kittens at Helsinki zoo",
      "title_ko": "헬싱키 동물원에서 팔라스고양이 세 마리 탄생",
      "title_original": "Pallas's cat gives birth to 3 kittens at Helsinki zoo",
      "triviality_score": 5
    },
    {
      "collected_at": "2026-07-03T18:02:03+09:00",
      "country": "ES",
      "country_ko": "스페인",
      "fallback_reason": "",
      "id": "e42daadd424c",
      "image_url": "https://s03.s3c.es/imag/_v0/1920x1048/6/2/7/1200x655_foios.jpg",
      "lang_original": "es",
      "lat": 39.5383,
      "lon": -0.3572,
      "processed_at": "2026-07-03T18:19:59+09:00",
      "provider_used": "opencode",
      "raw_excerpt": "Ferran Torres es un delantero del FC Barcelona que ahora ha llamado más la atención mediática por su paso por el Mundial de Fútbol 2026 jugando con la selección española. Eso ha hecho que muchos se animen a investigar un poco sobre él y, aunque vive en Gavà (la costa cerca de Barcelona), lo cierto es que sigue teniendo su refugio un poco más abajo, en el valenciano municipio de Foios.",
      "region": "Valencian Community",
      "source_name": "El Economista",
      "source_type": "google",
      "source_url": "https://www.eleconomista.es/evasion/noticias/13994771/07/26/el-refugio-de-ferran-torres-a-11-kilometros-de-valencia-un-pueblo-en-la-huerta-con-horchata-paella-y-cerca-de-la-playa.html",
      "summary_en": "Ferran Torres, FC Barcelona and Spain forward, keeps a refuge in Foios, a small town 11 km from Valencia. The town sits in the fertile huerta farmland and is famous for horchata, paella, and being close to the beach. His World Cup run made fans curious about this quiet hideaway.",
      "summary_ko": "FC 바르셀로나와 스페인 국가대표 공격수 페란 토레스가 발렌시아에서 11km 떨어진 포이오스(Foios)에 은신처를 두고 있다. 이 마을은 전통 음료 호르차타와 파에야로 유명한 후에르타(농업 지대)에 자리 잡고 있으며 해변과도 가깝다. 그의 월드컵 활약 이후 많은 팬들이 이 조용한 은신처에 관심을 보이기 시작했다.",
      "title_en": "Ferran Torres' hideaway 11 km from Valencia: a small town with horchata, paella and beach",
      "title_ko": "발렌시아서 11km, 페란 토레스의 은신처: 호르차타와 파에야 있는 작은 마을",
      "title_original": "El refugio de Ferran Torres a 11 kilómetros de Valencia: un pueblo en la huerta con horchata, paella y cerca de la playa - El Economista",
      "triviality_score": 4
    },
    {
      "collected_at": "2026-07-03T18:02:04+09:00",
      "country": "IT",
      "country_ko": "이탈리아",
      "fallback_reason": "",
      "id": "1e065ba37b63",
      "image_url": "https://www.lanazione.it/image-service/view/acePublic/alias/contentid/OTk2ZDY4YTEtYzljZS00/0/palomar-la-casa-della-cultura-di-san-giovanni.jpg?f=16:9&w=1200&h=675",
      "lang_original": "it",
      "lat": 43.564,
      "lon": 11.533,
      "processed_at": "2026-07-03T18:20:14+09:00",
      "provider_used": "opencode",
      "raw_excerpt": "la mostra sarà inaugurata a San Giovanni domani alle 11.",
      "region": "Tuscany",
      "source_name": "La Nazione",
      "source_type": "google",
      "source_url": "https://www.lanazione.it/arezzo/cronaca/paesaggio-del-valdarno-a-palomar-undici-artisti-raccontano-il-paesaggio-del-territorio-wnaams2t",
      "summary_en": "A new art exhibition called 'Paesaggio del Valdarno' opens tomorrow at 11 AM in San Giovanni. Eleven artists show works about the local landscape and territory.",
      "summary_ko": "새로운 예술 전시회 'Paesaggio del Valdarno(발다르노 풍경)'가 내일 오전 11시 산조반니에서 개막한다. 11명의 예술가들이 지역 풍경과 영토를 주제로 한 작품을 선보인다.",
      "title_en": "Eleven artists tell the story of Valdarno landscape at Palomar exhibition",
      "title_ko": "발다르노 풍경展, 팔로마르에서 예술가 11명이 지역을 이야기하다",
      "title_original": "“Paesaggio del Valdarno”, a Palomar undici artisti raccontano il il territorio - La Nazione",
      "triviality_score": 4
    },
    {
      "collected_at": "2026-07-03T18:02:27+09:00",
      "country": "ES",
      "country_ko": "스페인",
      "fallback_reason": "",
      "id": "5f86ae396d02",
      "image_url": "https://assets.thelocal.com/cdn-cgi/rs:fit:1200/quality:75/plain/https://apiwp.thelocal.com/wp-content/uploads/2026/07/watermarks-logo-AFP__20240717__364E4A3__v1__MidRes__SpainSeaPollution.jpg@webp",
      "lang_original": "en",
      "lat": null,
      "lon": null,
      "processed_at": "2026-07-03T18:20:36+09:00",
      "provider_used": "opencode",
      "raw_excerpt": "Environmental groups in Spain have handed out nearly 50 dreaded 'black flag' awards to beaches in Spain, with many suffering from pollution in popular tourist areas.",
      "region": null,
      "source_name": "The Local Spain",
      "source_type": "rss",
      "source_url": "https://www.thelocal.es/20260703/map-the-48-beaches-in-spain-to-avoid-this-summer",
      "summary_en": "Environmental groups gave nearly 50 'black flag' awards to Spanish beaches. Many suffer from pollution in popular tourist areas.",
      "summary_ko": "스페인 환경 단체들이 48곳의 해변에 '검은 깃발' 등급을 부여했다. 주요 관광지의 많은 해변이 오염 문제를 겪고 있다.",
      "title_en": "Map shows 48 polluted beaches in Spain to avoid this summer",
      "title_ko": "스페인 여름 피해야 할 해변 48곳 공개",
      "title_original": "MAP: The 48 beaches in Spain to avoid this summer",
      "triviality_score": 3
    },
    {
      "collected_at": "2026-07-03T18:02:31+09:00",
      "country": "NL",
      "country_ko": "네덜란드",
      "fallback_reason": "",
      "id": "a7877f4fb8c5",
      "image_url": "https://www.dutchnews.nl/wpcms/wp-content/uploads/2026/07/Depositphotos_163082384_S-e1783068127317.jpg",
      "lang_original": "en",
      "lat": 50.9,
      "lon": 5.9,
      "processed_at": "2026-07-03T18:21:00+09:00",
      "provider_used": "opencode",
      "raw_excerpt": "One of the last independent breweries in the Netherlands, Limburg-based Gulpener, has been taken over by Grolsch, the companies announced in a statement. “The beer market has changed a lot in recent years. As an independent brewer, it is becoming more and more challenging to continue growing on your own,” Gulpener said. The company has existed as a family run business for more than 200 years. “If you don’t change anything, you eventually hit a wall, and we want to...",
      "region": "Limburg",
      "source_name": "DutchNews.nl",
      "source_type": "rss",
      "source_url": "https://www.dutchnews.nl/2026/07/independent-brewery-gulpener-taken-over-by-grolsch/",
      "summary_en": "Gulpener, one of the last independent breweries in the Netherlands, has been acquired by Grolsch. The 200-year-old family business from Limburg said it cannot keep growing on its own in the changing beer market.",
      "summary_ko": "네덜란드에서 마지막까지 남아 있던 독립 양조장 중 하나인 림뷔르흐의 굴페너가 그롤쉬에 인수됐다. 200년 넘게 가족이 운영해 온 이 회사는 변화하는 맥주 시장에서 홀로 성장하기 어렵다고 밝혔다.",
      "title_en": "Family brewery Gulpener taken over by Grolsch",
      "title_ko": "가족 양조장 굴페너, 그롤쉬에 인수되다",
      "title_original": "Independent brewery Gulpener taken over by Grolsch",
      "triviality_score": 4
    },
    {
      "collected_at": "2026-07-03T18:02:31+09:00",
      "country": "AU",
      "country_ko": "호주",
      "fallback_reason": "",
      "id": "d97162d48d25",
      "image_url": "https://live-production.wcms.abc-cdn.net.au/bb2f50187a7e8372de01ab9781c695aa?impolicy=wcms_watermark_news&cropH=2813&cropW=5000&xPos=0&yPos=84&width=862&height=485&imformat=generic",
      "lang_original": "en",
      "lat": -12.4634,
      "lon": 130.8456,
      "processed_at": "2026-07-03T18:21:23+09:00",
      "provider_used": "opencode",
      "raw_excerpt": "Manuel Brown has admitted his underage son drove his personal car, one week after failing to disclose the matter when asked by the media, and says he is considering resigning from his shadow portfolios.",
      "region": "Northern Territory",
      "source_name": "ABC Australia News",
      "source_type": "rss",
      "source_url": "https://www.abc.net.au/news/2026-07-03/nt-labor-politician-manuel-brown-admits-underage-son-drove-car/106877394",
      "summary_en": "A senior Northern Territory Labor politician admitted his underage son drove his personal car. He did not tell reporters about it when first asked. Brown is now thinking about resigning from his shadow portfolios.",
      "summary_ko": "노던테러토리 노동당 고위 정치인 마누엘 브라운이 미성년 아들이 자신의 승용차를 몰았다는 사실을 인정했다. 그는 언론에 처음 질문을 받았을 때 이 사실을 밝히지 않았다가 뒤늦게 시인했다. 브라운은 현재 섀도우 장관직 사임을 고려 중이다.",
      "title_en": "NT shadow minister admits underage son drove his car",
      "title_ko": "NT 노동당 정치인, 미성년 아들 차량 운전 시인…사임 고려",
      "title_original": "NT shadow minister admits underage son drove car, considers resignation",
      "triviality_score": 4
    },
    {
      "collected_at": "2026-07-03T18:02:33+09:00",
      "country": "FI",
      "country_ko": "핀란드",
      "fallback_reason": "",
      "id": "3dd1df07b8cf",
      "image_url": "https://img.img-cdn.yle.fi/crop_extract,w_3940,h_2213,x_0,y_0/crop_fill,w_1200,h_628/f_auto/39-16686886a43516bf0359/1782797051",
      "lang_original": "en",
      "lat": null,
      "lon": null,
      "processed_at": "2026-07-03T18:22:08+09:00",
      "provider_used": "opencode",
      "raw_excerpt": "Outdoor festival organisers are bracing for potentially stormy weather this weekend.",
      "region": null,
      "source_name": "YLE News",
      "source_type": "rss",
      "source_url": "https://yle.fi/a/74-20234685",
      "summary_en": "Outdoor festival organisers in Finland are preparing for possible thunderstorms this weekend. The weather could affect events at several busy festivals across the country.",
      "summary_ko": "핀란드 야외 축제 주최측이 주말 천둥번개 가능성에 대비하고 있다. 악천후가 전국 여러 축제 일정에 영향을 줄 수 있다.",
      "title_en": "Thunderstorms expected for Finland festival weekend",
      "title_ko": "핀란드 축제 주말, 천둥번개 예보",
      "title_original": "Thunderstorms on the way for busy Finnish festival weekend",
      "triviality_score": 4
    },
    {
      "collected_at": "2026-07-03T18:02:33+09:00",
      "country": "IN",
      "country_ko": "인도",
      "fallback_reason": "",
      "id": "bd6903e14647",
      "image_url": "https://th-i.thgim.com/public/news/national/andhra-pradesh/bw38qm/article71177836.ece/alternates/LANDSCAPE_1200/Rush.jpeg",
      "lang_original": "en",
      "lat": 18.1079,
      "lon": 83.3953,
      "processed_at": "2026-07-03T18:22:19+09:00",
      "provider_used": "opencode",
      "raw_excerpt": "The Jana Sena Party has extended the deadline to July 5 for applications for party posts in the Vizianagaram parliamentary constituency, drawing over 1,200.",
      "region": "Andhra Pradesh",
      "source_name": "The Hindu National",
      "source_type": "rss",
      "source_url": "https://www.thehindu.com/news/national/andhra-pradesh/jana-sena-extends-deadline-to-july-5-for-party-posts-in-vizianagaram/article71177503.ece",
      "summary_en": "The Jana Sena Party has pushed the application deadline to July 5 for party positions in the Vizianagaram constituency. More than 1,200 people have already applied.",
      "summary_ko": "자나세나당이 비지아나가람 지역구 당직 모집 마감일을 7월 5일로 연장했다. 현재까지 1,200명 이상이 지원했다.",
      "title_en": "Jana Sena extends deadline for party posts in Vizianagaram",
      "title_ko": "비지아나가람 선거구 당직 신청, 자나세나파 마감 연장",
      "title_original": "Jana Sena extends deadline to July 5 for party posts in Vizianagaram",
      "triviality_score": 3
    },
    {
      "collected_at": "2026-07-03T18:03:13+09:00",
      "country": "AU",
      "country_ko": "호주",
      "fallback_reason": "",
      "id": "e8c2d4a6dd19",
      "image_url": "https://dam.mediacorp.sg/image/upload/s--5piQ1Equ--/c_crop,h_562,w_1000,x_0,y_9/c_fill,g_auto,h_676,w_1200/fl_relative,g_south_east,l_one-cms:core:watermark:ap_data-1,w_0.1/f_auto,q_auto/v1/one-cms/core/Australia_Shark_Attacks_35827.jpg?itok=KiTSBp3i",
      "lang_original": "en",
      "lat": -33.8688,
      "lon": 151.2093,
      "processed_at": "2026-07-03T18:23:17+09:00",
      "provider_used": "opencode",
      "raw_excerpt": "The drones only report bull, tiger and white sharks, species considered most likely to attack humans.",
      "region": "Sydney, New South Wales",
      "source_name": "CNA Singapore",
      "source_type": "rss",
      "source_url": "https://www.channelnewsasia.com/world/australia-drone-spots-sharks-beach-attack-6230146",
      "summary_en": "Drones spotted 73 sharks off Sydney beaches in just two days. The drones only track bull, tiger, and white sharks, the species considered most likely to attack humans.",
      "summary_ko": "시드니 해변 앞바다에서 드론이 이틀 만에 상어 73마리를 발견했습니다. 드론은 사람을 공격할 가능성이 가장 높은 황소상어, 호랑이상어, 백상어만 추적합니다.",
      "title_en": "Drones spot 73 sharks off Sydney beaches in two days",
      "title_ko": "시드니 해변 앞바다, 드론이 이틀 만에 상어 73마리 발견",
      "title_original": "Drones spot sharks 73 times in two days off Sydney beaches",
      "triviality_score": 4
    },
    {
      "collected_at": "2026-07-03T20:01:48+09:00",
      "country": "FR",
      "country_ko": "프랑스",
      "fallback_reason": "",
      "id": "1050e8e32cd3",
      "image_url": "https://assets.thelocal.com/cdn-cgi/rs:fit:1200/quality:75/plain/https://apiwp.thelocal.com/wp-content/uploads/2026/07/watermarks-logo-vers.jpg@webp",
      "lang_original": "en",
      "lat": null,
      "lon": null,
      "processed_at": "2026-07-03T20:17:20+09:00",
      "provider_used": "opencode",
      "raw_excerpt": "This French expression doesn't actually mean you're pulling the worms out of someone's nose.",
      "region": null,
      "source_name": "The Local France",
      "source_type": "rss",
      "source_url": "https://www.thelocal.fr/20260703/french-expression-of-the-day-tirer-les-vers-du-nez",
      "summary_en": "This French expression does not actually mean pulling worms out of someone's nose. It is a common French idiom with a surprising real meaning. Language learners will enjoy this curious phrase.",
      "summary_ko": "이 프랑스어 표현은 문자 그대로 '코에서 벌레를 꺼내다'라는 뜻이 아닙니다. 전혀 다른 의미를 가진 일상적인 프랑스 관용구입니다. 언어 학습자들이 재미있어 할 만한 기발한 표현입니다.",
      "title_en": "French Expression: Tirer les vers du nez",
      "title_ko": "프랑스어 표현 'Tirer les vers du nez'",
      "title_original": "French Expression of the Day: Tirer les vers du nez",
      "triviality_score": 5
    },
    {
      "collected_at": "2026-07-03T20:01:50+09:00",
      "country": "IT",
      "country_ko": "이탈리아",
      "fallback_reason": "",
      "id": "a43c963155e5",
      "image_url": "https://assets.thelocal.com/cdn-cgi/rs:fit:1200/quality:75/plain/https://apiwp.thelocal.com/wp-content/uploads/2020/11/watermarks-logo-aca549543e490cf275ac7bcc7ef6d23d3b7bcde9f919a6584686524e0f3a7e85.jpg@webp",
      "lang_original": "en",
      "lat": 40.85,
      "lon": 14.27,
      "processed_at": "2026-07-03T20:17:48+09:00",
      "provider_used": "opencode",
      "raw_excerpt": "Slow down and take the time to stroll through learning this word.",
      "region": "Campania",
      "source_name": "The Local Italy",
      "source_type": "rss",
      "source_url": "https://www.thelocal.it/20201112/italian-word-of-the-day-struscio",
      "summary_en": "Struscio is an Italian word that means a slow, aimless stroll through city streets. It is a tradition in Naples where people walk together in the evening. The word encourages you to slow down and enjoy small moments.",
      "summary_ko": "스트루쇼(Struscio)는 목적 없이 도시 거리를 천천히 걷는 것을 뜻하는 이탈리아어입니다. 나폴리에서는 사람들이 저녁에 함께 거리를 거니는 전통에서 이 단어가 쓰입니다. 느긋하게 걸으며 소소한 순간을 즐기라는 의미를 담고 있습니다.",
      "title_en": "Italian word of the day: 'Struscio'",
      "title_ko": "오늘의 이탈리아어 단어: '스트루쇼'",
      "title_original": "Italian word of the day: 'Struscio'",
      "triviality_score": 5
    },
    {
      "collected_at": "2026-07-03T20:01:52+09:00",
      "country": "NO",
      "country_ko": "노르웨이",
      "fallback_reason": "",
      "id": "f337c5cefbe7",
      "image_url": "https://assets.thelocal.com/cdn-cgi/rs:fit:1200/quality:75/plain/https://apiwp.thelocal.com/wp-content/uploads/2023/06/watermarks-logo-Lofoten-cabin-Andrew-Slifkin-Unsplash.jpg@webp",
      "lang_original": "en",
      "lat": null,
      "lon": null,
      "processed_at": "2026-07-03T20:18:24+09:00",
      "provider_used": "opencode",
      "raw_excerpt": "There are several great opportunities to go on a free overnight trip in Norway, if you know where to look.",
      "region": null,
      "source_name": "The Local Norway",
      "source_type": "rss",
      "source_url": "https://www.thelocal.no/20230619/how-to-enjoy-a-free-overnight-trip-in-the-norwegian-wilderness-this-summer",
      "summary_en": "You can enjoy a free overnight stay in the Norwegian wilderness this summer. There are several great places if you know where to look. This article shares tips on how to plan your trip.",
      "summary_ko": "노르웨이의 야생 자연에서 무료로 하룻밤을 보낼 수 있는 좋은 기회가 여러 곳 있다. 다만 좋은 장소를 아는 것이 중요하다. 이 기사는 여름철 무료 야영을 계획하는 팁을 소개한다.",
      "title_en": "Free overnight trips in the Norwegian wilderness this summer",
      "title_ko": "노르웨이 자연 속 무료 야영, 이렇게 즐겨보세요",
      "title_original": "How to enjoy a free overnight trip in the Norwegian wilderness this summer",
      "triviality_score": 4
    }
  ]
}
