{
  "version": 2,
  "built_at": "2026-06-20T08:25:29+09:00",
  "page": 1,
  "page_size": 20,
  "count": 20,
  "items": [
    {
      "collected_at": "2026-06-20T00:03:46+09:00",
      "country": "CA",
      "country_ko": "캐나다",
      "fallback_reason": "",
      "id": "56138becd517",
      "image_url": "https://i.cbc.ca/ais/1.4443610,1631129365000/full/max/0/default.jpg?im=Crop%2Crect%3D%280%2C0%2C1280%2C720%29%3BResize%3D620",
      "lang_original": "en",
      "lat": 46.3914,
      "lon": -62.7507,
      "processed_at": "2026-06-20T08:23:32+09:00",
      "provider_used": "opencode",
      "raw_excerpt": "Pan-seared scallops have been a top-selling menu item at New Glasgow Lobster Suppers — second only to lobster.",
      "region": "Prince Edward Island",
      "source_name": "CBC Canada",
      "source_type": "rss",
      "source_url": "https://www.cbc.ca/news/canada/prince-edward-island/pei-scallops-price-availability-menu-change-summer-2026-9.7240529",
      "summary_en": "Pan-seared scallops are a top seller at New Glasgow Lobster Suppers, second only to lobster. Soaring prices and scarce supply are forcing some Prince Edward Island restaurants to remove the dish this summer. Restaurant owners hope the shortage is temporary and will resolve next year.",
      "summary_ko": "팬 시어드 가리비는 PEI 뉴글래스고 랍스터 저녁식사에서 랍스터 다음으로 잘 팔리는 메뉴였다. 하지만 가격이 치솟고 공급이 달리면서 일부 현지 레스토랑들이 이번 여름 가리비 요리를 메뉴에서 제거하고 있다. 업주들은 이번 부족 사태가 일시적이길 바라고 있다.",
      "title_en": "High scallop prices force some P.E.I. restaurants to take dish off menus",
      "title_ko": "가리비 가격 폭등에 PEI 레스토랑들 '메뉴서 내립니다'",
      "title_original": "Scallop scarcity: Some P.E.I. restaurants removing the dish from menus as prices soar",
      "triviality_score": 3
    },
    {
      "collected_at": "2026-06-17T09:18:09+09:00",
      "country": "AT",
      "country_ko": "오스트리아",
      "id": "8a4055c6d8fd",
      "image_url": "https://www.horizont.at/news/media/14/Is-Vienna-Dull-133019.jpeg",
      "lang_original": "de",
      "lat": 48.2082,
      "lon": 16.3738,
      "processed_at": "2026-06-17T15:56:02+09:00",
      "raw_excerpt": "WienTourismus hat die Bewohner:innen des schottischen Dorfs Dull eingeladen, um im ruhigsten Monat des Jahres zu prüfen, ob die Stadt tatsächlich langweilig ist - und erhält ein klares Urteil.",
      "region": "Vienna",
      "source_name": "Horizont",
      "source_type": "google",
      "source_url": "https://www.horizont.at/marketing/news/langeweile-klischee-wien-laesst-das-schottische-dorf-dull-entscheiden-wie-dull-die-stadt-ist-100805",
      "summary_en": "Vienna Tourism invited people from Dull, a small Scottish village, to visit during the quietest month of the year. They were asked to judge whether the city is really boring, and they gave a clear verdict.",
      "summary_ko": "빈 관광청은 한 해 중 가장 조용한 달에 스코틀랜드의 작은 마을 덜 주민들을 초대했다. 빈이 정말 지루한 도시인지 판단해 달라는 취지였고, 주민들은 분명한 평가를 내렸다.",
      "title_en": "Vienna Asks Dull Village to Judge Its Boring Image",
      "title_ko": "빈, 스코틀랜드 덜 마을에 지루한 도시인지 물었다",
      "title_original": "Langeweile-Klischee: Wien lässt das schottische Dorf Dull entscheiden, wie \"dull\" die Stadt ist - Horizont",
      "triviality_score": 5
    },
    {
      "collected_at": "2026-06-17T09:18:04+09:00",
      "country": "FI",
      "country_ko": "핀란드",
      "id": "aeb1b22224ee",
      "image_url": "https://images.sanoma-sndp.fi/ad47c40f103a749de3da67c67a23a4c8/some/hs-default.jpg",
      "lang_original": "fi",
      "lat": 60.205,
      "lon": 24.963,
      "processed_at": "2026-06-17T15:55:10+09:00",
      "raw_excerpt": "Voiko tuhansien ihmisten kaupunginosa olla yhteisö? Kävimme Kumpulassa testaamassa.",
      "region": "Kumpula, Helsinki",
      "source_name": "HS.fi",
      "source_type": "google",
      "source_url": "https://www.hs.fi/helsinki/art-2000011238594.html",
      "summary_en": "HS.fi visits Kumpula, a district in Helsinki, to ask if a place with thousands of people can still feel like a community. Locals describe a village-like life where children run from one home to another.",
      "summary_ko": "HS.fi는 헬싱키의 쿰풀라를 찾아 수천 명이 사는 동네도 공동체가 될 수 있는지 살펴봤습니다. 주민들은 아이들이 집집마다 오가며 노는, 마을 같은 생활을 이야기합니다.",
      "title_en": "A Village Feeling in Helsinki",
      "title_ko": "헬싱키 속 마을 같은 동네",
      "title_original": "Hyvät ihmiset | Helsingissä on kylä, jossa ”lapset juoksevat huushollista toiseen” - HS.fi",
      "triviality_score": 5
    },
    {
      "collected_at": "2026-06-17T12:03:36+09:00",
      "country": "NO",
      "country_ko": "노르웨이",
      "id": "8eef28c5a87f",
      "image_url": "https://g.acdn.no/obscura/API/dynamic/r1/ece5/tr_2000_2000_s_f/1766142757000/avio/2025/12/19/12/Bar%2Bgruppe%2Bred%2B2.JPG?chk=F62BC2",
      "lang_original": "no",
      "lat": 59.9139,
      "lon": 10.7522,
      "processed_at": "2026-06-17T16:09:41+09:00",
      "raw_excerpt": "«Last Train, di gamle hore. Jeg elsker deg», skriver «huspsykolog» Pål Erik Gulliksrud i boka oppkalt etter baren.",
      "region": "Oslo",
      "source_name": "Avisa Oslo",
      "source_type": "google",
      "source_url": "https://www.ao.no/5-128-1216598",
      "summary_en": "The legendary Oslo bar Last Train has survived for more than 40 years. A new book named after the bar includes loving words from Pål Erik Gulliksrud, who calls it impossible to kill.",
      "summary_ko": "오슬로의 전설적인 바 Last Train이 40년 넘게 살아남았다. 바 이름을 딴 새 책에는 팔 에리크 굴릭스루드가 이곳을 향한 애정과 함께 쉽게 사라지지 않을 곳이라고 적었다.",
      "title_en": "Oslo bar Last Train turns 40",
      "title_ko": "오슬로의 전설적 바 Last Train, 40년 넘게 건재",
      "title_original": "Store stjerner vanker her. Den legendariske baren har overlevd i over 40 år: – Umulig å drepe - Avisa Oslo",
      "triviality_score": 5
    },
    {
      "collected_at": "2026-06-18T04:13:40+09:00",
      "country": "FR",
      "country_ko": "프랑스",
      "id": "d55a422ab060",
      "image_url": "https://www.petit-bulletin.fr/medias/articles/2024-06-12-14-40-07_Photopanoramique.jpeg",
      "lang_original": "fr",
      "lat": 45.837,
      "lon": 4.827,
      "processed_at": "2026-06-18T14:17:11+09:00",
      "raw_excerpt": "Le musée apocalyptique en plein air, La Demeure du chaos se prépare à changer de visage pour accueillir la troisième édition de la Battle du chaos le dimanche 16 juin.",
      "region": "Saint-Romain-au-Mont-d'Or, Lyon area",
      "source_name": "petit-bulletin.fr",
      "source_type": "google",
      "source_url": "https://www.petit-bulletin.fr/article-75777-demeure-du-chaos-champ-de-battle.html",
      "summary_en": "La Demeure du Chaos, an open-air apocalyptic museum near Lyon, is getting ready for a new look. It will host the third Battle du Chaos music event on Sunday, June 16.",
      "summary_ko": "리옹 근처의 야외 종말 테마 박물관 라 드뫼르 뒤 카오스가 새 단장을 준비하고 있다. 이곳에서는 6월 16일 일요일 세 번째 배틀 뒤 카오스 음악 행사가 열린다.",
      "title_en": "Chaos Museum Hosts a Music Battle",
      "title_ko": "카오스의 집에서 열리는 음악 배틀",
      "title_original": "Musiques Lyon - Demeure du chaos : champ de battle par Clémence Depresle - petit-bulletin.fr",
      "triviality_score": 5
    },
    {
      "collected_at": "2026-06-17T08:55:20+09:00",
      "country": "JP",
      "country_ko": "일본",
      "id": "fa71e86b7823",
      "image_url": "https://news.walkerplus.com/article/102452/566964_615.jpg",
      "lang_original": "ja",
      "lat": 43.0642,
      "lon": 141.3538,
      "processed_at": "2026-06-17T15:41:10+09:00",
      "raw_excerpt": "3/4土曜日、札幌駅前通りと北3条通りが交差するスポットに新しく誕生する「札幌フコク生命越山ビル」。このビルの地下1階か…",
      "region": "Sapporo, Hokkaido",
      "source_name": "ウォーカープラス",
      "source_type": "google",
      "source_url": "https://www.walkerplus.com/article/102452/",
      "summary_en": "Sitatte Sapporo is opening in the new Sapporo Fukoku Seimei Koshiyama Building. The site is near the crossing of Sapporo Station Street and North 3jo Street. It will include first Hokkaido locations and special limited menus.",
      "summary_ko": "시타테 삿포로가 새로 들어서는 삿포로 후코쿠생명 고시야마 빌딩에 문을 엽니다. 위치는 삿포로역 앞 거리와 북3조 거리가 만나는 곳 근처입니다. 홋카이도 첫 입점 매장과 한정 메뉴도 함께 선보입니다.",
      "title_en": "New Sitatte Sapporo Brings First Shops and Special Menus",
      "title_ko": "새 복합공간 시타테 삿포로, 첫 입점 매장과 한정 메뉴 선보여",
      "title_original": "sitatte sapporo(シタッテサッポロ)、道内初出店＆限定メニューもぞくぞく！ - ウォーカープラス",
      "triviality_score": 4
    },
    {
      "collected_at": "2026-06-17T09:18:30+09:00",
      "country": "AU",
      "country_ko": "호주",
      "id": "48f0e63ce9e3",
      "image_url": "https://live-production.wcms.abc-cdn.net.au/cc1479423c13f9b3b4ccad74b5ba1c0e?impolicy=wcms_watermark_news&cropH=2812&cropW=4999&xPos=0&yPos=0&width=862&height=485&imformat=generic",
      "lang_original": "en",
      "lat": -12.19,
      "lon": 136.78,
      "processed_at": "2026-06-17T15:57:45+09:00",
      "raw_excerpt": "The animated award-winning cartoon series Bluey has been translated into Yolŋu Matha, from north-east Arnhem Land, for NAIDOC Week.",
      "region": "north-east Arnhem Land, Northern Territory",
      "source_name": "ABC Australia News",
      "source_type": "rss",
      "source_url": "https://www.abc.net.au/news/2026-06-17/bluey-launches-in-yolnu-matha-for-naidoc-week/106803138",
      "summary_en": "The cartoon series Bluey has been translated into Yolŋu Matha. The language comes from north-east Arnhem Land, and the new version was made for NAIDOC Week.",
      "summary_ko": "만화 시리즈 블루이가 욜ŋ우 마타로 번역됐다. 이 언어는 호주 노던준주의 북동부 아넘랜드 지역에서 쓰이며, 이번 번역판은 NAIDOC 주간을 위해 만들어졌다.",
      "title_en": "Bluey Speaks Yolŋu Matha for the First Time",
      "title_ko": "블루이가 처음으로 욜ŋ우 마타로 말한다",
      "title_original": "Bluey speaks Yolŋu Matha for the first time",
      "triviality_score": 4
    },
    {
      "collected_at": "2026-06-17T09:18:24+09:00",
      "country": "DK",
      "country_ko": "덴마크",
      "id": "71c7706871c4",
      "image_url": "https://assets.thelocal.com/cdn-cgi/rs:fit:1200/quality:75/plain/https://apiwp.thelocal.com/wp-content/uploads/2026/06/watermarks-logo-billund.jpg@webp",
      "lang_original": "en",
      "lat": 55.6761,
      "lon": 12.5683,
      "processed_at": "2026-06-17T15:57:10+09:00",
      "raw_excerpt": "In one of her first summers in Denmark, Rushnan Binte Amin spent an entire week discovering the country through six separate day trips from Copenhagen. It changed the way she saw her adopted home.",
      "region": "Copenhagen",
      "source_name": "The Local Denmark",
      "source_type": "rss",
      "source_url": "https://www.thelocal.dk/20260616/one-week-six-breaks-how-i-discovered-denmark-through-day-trips-from-copenhagen",
      "summary_en": "Rushnan Binte Amin spent one summer week taking six day trips from Copenhagen. The short trips helped her see Denmark in a new way and feel closer to her adopted home.",
      "summary_ko": "루슈난 빈테 아민은 어느 여름, 코펜하겐에서 출발하는 당일치기를 일주일 동안 여섯 번 다녀왔다. 짧은 여행들은 그녀가 덴마크를 새롭게 바라보고, 정착한 나라를 더 가깝게 느끼게 했다.",
      "title_en": "Six Day Trips Changed How One Newcomer Saw Denmark",
      "title_ko": "여섯 번의 당일치기로 새롭게 본 덴마크",
      "title_original": "One week, six breaks: How I discovered Denmark through day trips",
      "triviality_score": 5
    },
    {
      "collected_at": "2026-06-17T14:08:41+09:00",
      "country": "AR",
      "country_ko": "아르헨티나",
      "id": "ea74d1e99655",
      "image_url": "https://www.memo.com.ar/files/image/85/85427/67f0fcd2d8477_600_315!.jpg?s=bbf05c142dede6aa1494ec81c8a03f53&d=1771795549",
      "lang_original": "es",
      "lat": -34.98,
      "lon": -67.69,
      "processed_at": "2026-06-17T16:28:56+09:00",
      "raw_excerpt": "Conocimos el Museo de Ciencias Naturales \"Rafael Reinoso\" en el distrito de Carmensa en General Alvear, ubicado dentro de un antiguo galpón de tren. El lugar fue reacondicionado y está poblado de especímenes de diferentes ambientes, gracias al cuidadoso y responsable trabajo de este reconocido taxidermista.",
      "region": "Carmensa, General Alvear, Mendoza",
      "source_name": "Noticias de Mendoza - Memo",
      "source_type": "google",
      "source_url": "https://www.memo.com.ar/cultura/un-museo-mendocino-dedicado-a-la-taxidermia/",
      "summary_en": "The Rafael Reinoso Natural Science Museum is in Carmensa, General Alvear, inside an old train shed. The restored space shows specimens from different natural areas, made through the careful work of a well-known taxidermist.",
      "summary_ko": "헤네랄 알베아르 카르멘사에 있는 라파엘 레이노소 자연과학박물관은 오래된 기차 창고 안에 자리하고 있다. 새로 손본 공간에는 여러 자연 환경의 표본들이 전시되어 있으며, 이름난 박제사의 세심한 작업으로 채워졌다.",
      "title_en": "A Mendoza Museum About Taxidermy",
      "title_ko": "박제술을 다룬 멘도사 지역 박물관",
      "title_original": "Un museo mendocino dedicado a la taxidermia - Noticias de Mendoza - Memo",
      "triviality_score": 5
    },
    {
      "collected_at": "2026-06-18T02:01:55+09:00",
      "country": "MX",
      "country_ko": "멕시코",
      "id": "4d62dede45d9",
      "image_url": "https://mexiconewsdaily.com/wp-content/uploads/2026/06/03-sm-Steamy-morning-at-El-Rincon.jpg",
      "lang_original": "en",
      "lat": null,
      "lon": null,
      "processed_at": "2026-06-18T10:16:49+09:00",
      "raw_excerpt": "Mexico's splitfin fish were on the brink of extinction, but are now being brought back to abundance by dedicated environmentalists.",
      "region": null,
      "source_name": "Mexico News Daily",
      "source_type": "rss",
      "source_url": "https://mexiconewsdaily.com/lifestyle/how-mexicos-celebrated-splitfin-fish-were-rescued-from-the-brink-of-extinction/",
      "summary_en": "Mexico's splitfin fish were close to extinction. Dedicated environmentalists are now helping the fish return in larger numbers.",
      "summary_ko": "멕시코의 스플릿핀 물고기는 멸종 위기 직전까지 몰렸습니다. 헌신적인 환경운동가들이 이 물고기가 다시 개체 수를 늘릴 수 있도록 돕고 있습니다.",
      "title_en": "Mexico's Splitfin Fish Make a Comeback",
      "title_ko": "멕시코 스플릿핀 물고기의 회복",
      "title_original": "How Mexico’s celebrated splitfin fish were rescued from the brink of extinction",
      "triviality_score": 4
    },
    {
      "collected_at": "2026-06-17T12:04:25+09:00",
      "country": "FI",
      "country_ko": "핀란드",
      "id": "0f616b2c1224",
      "image_url": "https://stplattaprod.blob.core.windows.net/etusivu64e62prod/styles/1_9_1200w_630h/azure/ostis_kartta_3_2.jpeg?itok=F_3O1fr9",
      "lang_original": "fi",
      "lat": 60.25,
      "lon": 25.19,
      "processed_at": "2026-06-17T16:14:10+09:00",
      "raw_excerpt": "Helsingin kaupunki suunnittelee Östersundomiin uusia asuin- työpaikka- ja luonnonsuojelualueita. Alueen osayleiskaavan luonnos perustuu laajoihin selvityksiin.",
      "region": "Helsinki",
      "source_name": "Helsingin kaupunki",
      "source_type": "google",
      "source_url": "https://www.hel.fi/fi/uutiset/ostersundomista-halutaan-luonnonlaheinen-raideliikenteen-pikkukaupunki-kaavaluonnosta-voi",
      "summary_en": "Helsinki is planning new homes, jobs, and nature protection areas in Ostersundom. The draft local plan is based on wide studies and can be commented on until the end of October.",
      "summary_ko": "헬싱키시는 외스테르순돔에 새 주거지, 일자리 공간, 자연보호구역을 계획하고 있다. 이 지역의 부분 종합계획 초안은 폭넓은 조사에 기반하며, 10월 말까지 의견을 낼 수 있다.",
      "title_en": "Helsinki Plans a Nature-Friendly Rail Town in Ostersundom",
      "title_ko": "헬싱키, 외스테르순돔에 자연 가까운 철도 마을 계획",
      "title_original": "Östersundomista halutaan luonnonläheinen raideliikenteen pikkukaupunki – kaavaluonnosta voi kommentoida lokakuun loppuun - Helsingin kaupunki",
      "triviality_score": 3
    },
    {
      "collected_at": "2026-06-18T08:02:53+09:00",
      "country": "CA",
      "country_ko": "캐나다",
      "id": "2020181568d8",
      "image_url": "https://i.cbc.ca/ais/a6f7c2a9-8c8d-4e46-a42d-cabf2df15e52,1781724785050/full/max/0/default.jpg?im=Crop%2Crect%3D%280%2C0%2C1920%2C1080%29%3BResize%3D620",
      "lang_original": "en",
      "lat": 46.3432,
      "lon": -72.543,
      "processed_at": "2026-06-19T13:02:07+09:00",
      "raw_excerpt": "The windows of the Mauricie Islamic Cultural Centre were smashed in an act of vandalism early Wednesday morning in Trois-Rivières, Que.",
      "region": "Trois-Rivières, Quebec",
      "source_name": "CBC Canada",
      "source_type": "rss",
      "source_url": "https://www.cbc.ca/news/canada/montreal/islamic-cultural-centre-vandalism-9.7239021",
      "summary_en": "Windows at the Mauricie Islamic Cultural Centre were smashed early Wednesday in Trois-Rivières, Quebec. The vandalism left people worried and hurt.",
      "summary_ko": "수요일 이른 아침 퀘벡주 트루아리비에르의 모리시 이슬람 문화 센터 창문이 깨졌다. 이 기물 파손으로 사람들이 걱정하고 상처를 받았다.",
      "title_en": "Mosque vandalized in Trois-Rivières",
      "title_ko": "트루아리비에르 모스크 기물 파손",
      "title_original": "Worry, hurt after mosque vandalized in Trois-Rivières, Que.",
      "triviality_score": 3
    },
    {
      "collected_at": "2026-06-18T10:04:49+09:00",
      "country": "JP",
      "country_ko": "일본",
      "fallback_reason": "",
      "id": "f170758ac3de",
      "image_url": "https://prcdn.freetls.fastly.net/release_image/158726/2/158726-2-8a14331be19c72458041aa2bf89a9739-3900x1950.png?format=jpeg&auto=webp&fit=bounds&width=2400&height=1260",
      "lang_original": "ja",
      "lat": 43.0618,
      "lon": 141.3545,
      "processed_at": "2026-06-19T14:22:58+09:00",
      "provider_used": "opencode",
      "raw_excerpt": "合同会社MATRIXのプレスリリース（2025年3月23日 15時52分）新たな飲食空間「札幌屋台村」が誕生!出店を希望される方々にご案内いたします。",
      "region": "Hokkaido",
      "source_name": "PR TIMES",
      "source_type": "google",
      "source_url": "https://prtimes.jp/main/html/rd/p/000000002.000158726.html",
      "summary_en": "A new food stall village called 'Sapporo Yatai Village' is opening in Sapporo, Hokkaido. The project operator MATRIX LLC is inviting people to open food stalls there. It aims to become a new local dining destination.",
      "summary_ko": "홋카이도 삿포로에 새로운 포장마차 거리 '삿포로 야타이촌'이 문을 엽니다. 운영사 매트릭스는 입점 희망자를 모집 중입니다. 지역 주민과 방문객을 위한 새로운 먹거리 공간이 될 전망입니다.",
      "title_en": "New 'Sapporo Yatai Village' Food Space Launches, Seeking Stall Operators",
      "title_ko": "삿포로에 '야타이촌' 새 푸드 공간 오픈…포장마차 운영자 모집",
      "title_original": "新たな飲食空間「札幌屋台村」が誕生!出店を希望される方々にご案内いたします。 | 合同会社MATRIXのプレスリリース - PR TIMES",
      "triviality_score": 4
    },
    {
      "collected_at": "2026-06-18T08:10:24+09:00",
      "country": "AT",
      "country_ko": "오스트리아",
      "fallback_reason": "",
      "id": "2ba79f30ec17",
      "image_url": "https://cdn.baunetz.de/www.baunetz.de/img/3/2/5/2/6/3/5/teaser-379ab1f32faac292.jpeg",
      "lang_original": "de",
      "lat": 47.8,
      "lon": 13.0,
      "processed_at": "2026-06-19T14:16:46+09:00",
      "provider_used": "opencode",
      "raw_excerpt": "BauNetz-Architektur-Meldung vom 19.02.2026: Wohnen zwischen Silotürmen / Umbau bei Salzburg von LP architektur - Aktuelle Architekturmeldungen aus dem In- und Ausland, täglich recherchiert von der BauNetz-Redaktion",
      "region": "Salzburg",
      "source_name": "BauNetz",
      "source_type": "google",
      "source_url": "https://www.baunetz.de/meldungen/Meldungen-Shortlist_bekanntgegeben_8340363.html?bild=3",
      "summary_en": "LP architektur turned old silo towers into homes near Salzburg, Austria. The project turns industrial buildings into living spaces. BauNetz shares the story of this unusual renovation.",
      "summary_ko": "LP architektur가 오스트리아 잘츠부르크 근처의 옛 사일로 타워를 주택으로 바꿨다. 산업용 건물을 주거 공간으로 재탄생시킨 프로젝트다. BauNetz가 이 이색적인 리모델링 소식을 전했다.",
      "title_en": "Living Between Silo Towers: A Renovation Near Salzburg",
      "title_ko": "사일로 타워 사이에 집을 짓다: 잘츠부르크 근교 LP architektur의 리모델링",
      "title_original": "Wohnen zwischen Silotürmen / Umbau bei Salzburg von LP architektur - Architektur und Architekten - News / Meldungen / Nachrichten - BauNetz",
      "triviality_score": 5
    },
    {
      "collected_at": "2026-06-18T06:05:04+09:00",
      "country": "US",
      "country_ko": "미국",
      "id": "508aded165d8",
      "image_url": "https://bloximages.newyork1.vip.townnews.com/northstarmonthly.com/content/tncms/assets/v3/editorial/3/b4/3b451060-7200-11e6-87d8-d35421ae4f3d/66e4989e8555d.preview.jpg?crop=1763%2C926%2C0%2C124&resize=1200%2C630&order=crop%2Cresize",
      "lang_original": "en",
      "lat": 44.3292,
      "lon": -72.1712,
      "processed_at": "2026-06-19T12:53:15+09:00",
      "raw_excerpt": "The town's name has intriguing origins linked to an English opera character, while its landscape offers stunning views of the Green and White Mountains.",
      "region": "Vermont",
      "source_name": "The North Star Monthly",
      "source_type": "google",
      "source_url": "https://www.northstarmonthly.com/kingdom_guide/town_profiles_history/peacham-charming-vermont-town-in-northeast-kingdom/article_3b451060-7200-11e6-87d8-d35421ae4f3d.html",
      "summary_en": "Peacham is a small Vermont town with a name tied to a character from an English opera. Its landscape offers wide views of the Green Mountains and the White Mountains.",
      "summary_ko": "피첨은 영국 오페라 속 인물과 관련된 이름을 가진 버몬트주의 작은 마을입니다. 이곳에서는 그린 산맥과 화이트 산맥의 넓은 풍경을 볼 수 있습니다.",
      "title_en": "Peacham's Name and Mountain Views",
      "title_ko": "영국 오페라 인물에서 온 피첨의 이름",
      "title_original": "Evolution of Peacham: From Pioneers to Present Day - The North Star Monthly",
      "triviality_score": 5
    },
    {
      "collected_at": "2026-06-17T18:01:53+09:00",
      "country": "IN",
      "country_ko": "인도",
      "id": "f6bbecc767e1",
      "image_url": "https://th-i.thgim.com/public/incoming/dygivu/article71112825.ece/alternates/LANDSCAPE_1200/PTI06_08_2024_000221A.jpg",
      "lang_original": "en",
      "lat": 22.9868,
      "lon": 87.855,
      "processed_at": "2026-06-17T18:13:31+09:00",
      "raw_excerpt": "TMC MP Saugata Roy urges Home Minister Amit Shah to address violent egg attacks on party leaders in West Bengal.",
      "region": "West Bengal",
      "source_name": "The Hindu National",
      "source_type": "rss",
      "source_url": "https://www.thehindu.com/news/national/west-bengal/tmcs-saugata-roy-writes-to-home-minister-amit-shah-over-egg-attacks-against-party-leaders/article71112402.ece",
      "summary_en": "TMC lawmaker Saugata Roy asked Home Minister Amit Shah to act on egg attacks against party leaders in West Bengal. He said the attacks were violent and needed attention.",
      "summary_ko": "트리나물 콩그레스 소속 사우가타 로이 의원이 서벵골에서 당 지도부를 겨냥한 계란 공격에 대응해 달라고 아미트 샤 내무장관에게 요청했다. 그는 이 공격이 폭력적이며 주의가 필요하다고 밝혔다.",
      "title_en": "Indian MP asks for action after egg attacks",
      "title_ko": "인도 의원, 정당 지도부 겨냥한 계란 공격 대응 요청",
      "title_original": "TMC’s Saugata Roy writes to Home Minister Amit Shah over ‘egg attacks’ against party leaders",
      "triviality_score": 3
    },
    {
      "collected_at": "2026-06-19T20:13:13+09:00",
      "country": "SE",
      "country_ko": "스웨덴",
      "fallback_reason": "",
      "id": "50f9e15af4d9",
      "image_url": "https://cdn.mos.cms.futurecdn.net/Guzzt4SJL5xrHJCjPeK5EG-2560-80.jpg",
      "lang_original": "en",
      "lat": 59.8586,
      "lon": 17.6389,
      "processed_at": "2026-06-20T06:19:58+09:00",
      "provider_used": "opencode",
      "raw_excerpt": "It was part of a space rock that created a dramatic fireball over Uppsala.",
      "region": "Uppsala",
      "source_name": "Live Science",
      "source_type": "google",
      "source_url": "https://www.livescience.com/iron-meteorite-recovered-sweden.html",
      "summary_en": "A lumpy 30-pound meteorite that created a dramatic fireball over Uppsala was recovered in a local village. It was part of a space rock that lit up the sky. Scientists confirmed it is an iron meteorite.",
      "summary_ko": "웁살라 상공에서 극적인 불덩이를 만든 30파운드짜리 운석이 인근 마을에서 수거됐다. 이 운석은 하늘을 밝게 수놓은 우주 암석의 일부였다. 과학자들은 이것이 철 운석임을 확인했다.",
      "title_en": "30-pound iron meteorite found in Swedish village after fireball",
      "title_ko": "스웨덴 마을에서 발견된 30파운드 철 운석",
      "title_original": "Lumpy, 30-pound meteorite that crashed in Sweden recovered in local village - Live Science",
      "triviality_score": 3
    },
    {
      "collected_at": "2026-06-17T12:03:42+09:00",
      "country": "AT",
      "country_ko": "오스트리아",
      "id": "43178d09c170",
      "image_url": "https://www.vienna.at/2026/05/Regions_KeyVisual_Sommer_Mitterbergblick_KeyVisual_Summer_View_Mitterberg16x9C_Zell_am_See-Kaprun.310634fd_original-vodl-10163669-16-9-1280x720.jpg?v=11cfa886",
      "lang_original": "de",
      "lat": 47.3235,
      "lon": 12.7968,
      "processed_at": "2026-06-17T16:10:26+09:00",
      "raw_excerpt": "Zell am See im Salzburger Pinzgau wurde vom US-Magazin „Travel + Leisure“ als eine der schönsten Kleinstädte Europas ausgezeichnet, wobei die beeindruckende natürliche Kulisse zwischen dem Zeller See und den Hohen Tauern hervorgehoben wird.",
      "region": "Salzburg Pinzgau",
      "source_name": "Vienna.at",
      "source_type": "google",
      "source_url": "https://www.vienna.at/das-ist-die-schoenste-kleinstadt-oesterreichs/10163669",
      "summary_en": "Zell am See in Salzburg's Pinzgau region was praised by Travel + Leisure as one of Europe's most beautiful small towns. The magazine highlighted its setting between Lake Zell and the Hohe Tauern mountains.",
      "summary_ko": "잘츠부르크 핀츠가우 지역의 첼암제가 Travel + Leisure가 꼽은 유럽의 아름다운 소도시 중 하나로 소개됐다. 이 매체는 첼러 호수와 호에 타우에른 산맥 사이에 자리한 자연 풍경을 높이 평가했다.",
      "title_en": "Zell am See Named Austria's Most Beautiful Small Town",
      "title_ko": "오스트리아의 아름다운 소도시로 뽑힌 첼암제",
      "title_original": "Das ist die schönste Kleinstadt Österreichs - Vienna.at",
      "triviality_score": 4
    },
    {
      "collected_at": "2026-06-17T20:11:06+09:00",
      "country": "AR",
      "country_ko": "아르헨티나",
      "id": "b6424fe3cd59",
      "image_url": "https://www.conicet.gov.ar/wp-content/uploads/Calaichthys-tehul.jpg",
      "lang_original": "es",
      "lat": null,
      "lon": null,
      "processed_at": "2026-06-17T22:22:03+09:00",
      "raw_excerpt": "Vivió en el Triásico medio y perteneció a una especie de la que no se tenía registro en Sudamérica.",
      "region": null,
      "source_name": "CONICET",
      "source_type": "google",
      "source_url": "https://www.conicet.gov.ar/?post_type=post&p=58674",
      "summary_en": "CONICET researchers found fossils of a fish more than 240 million years old. The fish lived in the Middle Triassic. It belonged to a species not recorded in South America before.",
      "summary_ko": "CONICET 연구진이 2억4천만 년이 넘은 물고기 화석을 발견했다. 이 물고기는 중기 트라이아스기에 살았다. 남아메리카에서는 기록된 적이 없던 종에 속한다.",
      "title_en": "CONICET researchers find 240-million-year-old fish fossils",
      "title_ko": "CONICET 연구진, 2억4천만 년 넘은 물고기 화석 발견",
      "title_original": "Investigadores del CONICET hallaron fósiles de un pez de más de 240 millones de años - CONICET",
      "triviality_score": 3
    },
    {
      "collected_at": "2026-06-18T00:06:25+09:00",
      "country": "MX",
      "country_ko": "멕시코",
      "id": "55b77494b74f",
      "image_url": "https://www.informador.mx/__export/1680640453948/sites/elinformador/img/2023/04/04/oaxaca_1_foto_de_matthew_essman_en_unsplash_monte_alban_crop1680640052656.jpg_2024461655.jpg",
      "lang_original": "es",
      "lat": null,
      "lon": null,
      "processed_at": "2026-06-18T08:20:40+09:00",
      "raw_excerpt": "Aquellos lugares que llenan de gratas experiencias son destinos a los que se desea volver en cualquier oportunidad de viaje",
      "region": "Quintana Roo, Oaxaca, and Jalisco",
      "source_name": "El Informador",
      "source_type": "google",
      "source_url": "https://www.informador.mx/estilo/Viajes-2023-Quintana-Roo-Oaxaca-y-Jalisco-son-los-destinos-a-los-que-los-viajeros-desean-regresar-20230404-0107.html",
      "summary_en": "The article says Quintana Roo, Oaxaca, and Jalisco are places travelers want to visit again. It says places with good experiences become destinations people hope to return to on future trips.",
      "summary_ko": "기사에 따르면 킨타나로오, 오악사카, 할리스코는 여행자들이 다시 방문하고 싶어 하는 지역이다. 좋은 경험을 남긴 장소는 다음 여행에서도 다시 찾고 싶은 목적지가 된다고 소개한다.",
      "title_en": "Travelers Want to Return to Quintana Roo, Oaxaca, and Jalisco",
      "title_ko": "여행자들이 다시 찾고 싶은 멕시코 세 지역",
      "title_original": "Quintana Roo, Oaxaca y Jalisco son los destinos a los que los viajeros desean regresar - El Informador",
      "triviality_score": 3
    }
  ]
}
