{
  "version": 2,
  "built_at": "2026-06-19T14:26:44+09:00",
  "page": 10,
  "page_size": 20,
  "count": 20,
  "items": [
    {
      "collected_at": "2026-06-18T12:01:56+09:00",
      "country": "SG",
      "country_ko": "싱가포르",
      "fallback_reason": "",
      "id": "c36be82e1fe9",
      "image_url": "https://dam.mediacorp.sg/image/upload/s--E5h42A7L--/c_crop,h_900,w_1600,x_0,y_96/c_fill,g_auto,h_676,w_1200/f_auto,q_auto/v1/mediacorp/cna/image/2024/11/25/iStock-1365204248.jpg?itok=VmMk2uH0",
      "lang_original": "en",
      "lat": null,
      "lon": null,
      "processed_at": "2026-06-19T14:26:26+09:00",
      "provider_used": "opencode",
      "raw_excerpt": "Five of the public holidays in 2027 fall on Friday, Sunday or Monday.",
      "region": null,
      "source_name": "CNA Singapore",
      "source_type": "rss",
      "source_url": "https://www.channelnewsasia.com/singapore/public-holidays-2027-singapore-ministry-manpower-6191966",
      "summary_en": "Singapore's Ministry of Manpower has released the public holiday dates for 2027. Five of the 11 holidays fall on a Friday, Sunday or Monday, giving five long weekends.",
      "summary_ko": "싱가포르 인력부가 2027년 공휴일 일정을 발표했다. 11개 공휴일 중 5개가 금요일, 일요일 또는 월요일에 해당해 총 5번의 긴 연휴가 생긴다.",
      "title_en": "Singapore public holiday dates for 2027 released",
      "title_ko": "2027년 싱가포르 공휴일 발표, 5개 연휴 기대",
      "title_original": "Singapore public holiday dates for 2027 released, with 5 long weekends",
      "triviality_score": 4
    },
    {
      "collected_at": "2026-06-17T08:55:03+09:00",
      "country": "AT",
      "country_ko": "오스트리아",
      "id": "75a5a9b3e6ba",
      "image_url": "https://assets.thelocal.com/cdn-cgi/rs:fit:1200/quality:75/plain/https://apiwp.thelocal.com/wp-content/uploads/2026/06/watermarks-logo-TL-Word-of-the-day-copy.jpg@webp",
      "lang_original": "en",
      "lat": null,
      "lon": null,
      "processed_at": "2026-06-17T15:39:56+09:00",
      "raw_excerpt": "Some football expressions are useful long after the match is over. One of the best examples is am Ball bleiben.",
      "region": null,
      "source_name": "The Local Austria",
      "source_type": "rss",
      "source_url": "https://www.thelocal.at/20260616/german-expression-of-the-day-am-ball-bleiben",
      "summary_en": "The Local Austria looks at a German expression from football. It says some football phrases stay useful after the match, including \"am Ball bleiben.\"",
      "summary_ko": "The Local Austria가 축구에서 나온 독일어 표현을 소개한다. 경기 후에도 쓸 수 있는 축구 표현이 있으며, 그 예로 \"am Ball bleiben\"을 든다.",
      "title_en": "German phrase: am Ball bleiben",
      "title_ko": "독일어 표현: am Ball bleiben",
      "title_original": "German Expression of the Day: am Ball bleiben",
      "triviality_score": 3
    },
    {
      "collected_at": "2026-06-17T09:18:12+09:00",
      "country": "US",
      "country_ko": "미국",
      "id": "7e0d8ca3ae04",
      "image_url": "https://gray-wcax-prod.gtv-cdn.com/resizer/v2/https%3A%2F%2Fdo0bihdskp9dy.cloudfront.net%2F05-25-2026%2Ft_f446c0a3e6b7499694100a3d17b9a9a4_name_file_1280x720_2000_v3_1_.jpg?auth=ef7f2ef84647db3b91c1404269a037f19960550b7c79e198e0d6051950370f90&width=1200&height=600&smart=true",
      "lang_original": "en",
      "lat": 44.0,
      "lon": -72.7,
      "processed_at": "2026-06-17T15:56:30+09:00",
      "raw_excerpt": "Vermont is home to more than 45 cheesemakers and produces some of the best cheese in the country. About a year ago, one of the state’s most historic brands got a chance to continue its legacy by teaming up with another to bring its cheese into the future.",
      "region": "Vermont",
      "source_name": "WCAX",
      "source_type": "google",
      "source_url": "https://www.wcax.com/video/2026/05/25/made-vermont-grafton-village-cheese/",
      "summary_en": "Vermont has more than 45 cheesemakers and is known for some of the best cheese in the country. About a year ago, historic Grafton Village Cheese teamed up with another brand to keep its legacy going and bring its cheese into the future.",
      "summary_ko": "버몬트에는 45곳이 넘는 치즈 제조업체가 있으며, 미국에서도 손꼽히는 치즈 생산지로 알려져 있습니다. 약 1년 전, 오랜 역사를 지닌 그래프턴 빌리지 치즈는 다른 브랜드와 손잡고 전통을 이어 가며 치즈의 미래를 준비하게 됐습니다.",
      "title_en": "Grafton Village Cheese Looks to the Future",
      "title_ko": "그래프턴 빌리지 치즈, 전통을 이어 미래로",
      "title_original": "Made in Vermont: Grafton Village Cheese - WCAX",
      "triviality_score": 5
    },
    {
      "collected_at": "2026-06-18T08:02:53+09:00",
      "country": "CA",
      "country_ko": "캐나다",
      "id": "2020181568d8",
      "image_url": "https://i.cbc.ca/ais/a6f7c2a9-8c8d-4e46-a42d-cabf2df15e52,1781724785050/full/max/0/default.jpg?im=Crop%2Crect%3D%280%2C0%2C1920%2C1080%29%3BResize%3D620",
      "lang_original": "en",
      "lat": 46.3432,
      "lon": -72.543,
      "processed_at": "2026-06-19T13:02:07+09:00",
      "raw_excerpt": "The windows of the Mauricie Islamic Cultural Centre were smashed in an act of vandalism early Wednesday morning in Trois-Rivières, Que.",
      "region": "Trois-Rivières, Quebec",
      "source_name": "CBC Canada",
      "source_type": "rss",
      "source_url": "https://www.cbc.ca/news/canada/montreal/islamic-cultural-centre-vandalism-9.7239021",
      "summary_en": "Windows at the Mauricie Islamic Cultural Centre were smashed early Wednesday in Trois-Rivières, Quebec. The vandalism left people worried and hurt.",
      "summary_ko": "수요일 이른 아침 퀘벡주 트루아리비에르의 모리시 이슬람 문화 센터 창문이 깨졌다. 이 기물 파손으로 사람들이 걱정하고 상처를 받았다.",
      "title_en": "Mosque vandalized in Trois-Rivières",
      "title_ko": "트루아리비에르 모스크 기물 파손",
      "title_original": "Worry, hurt after mosque vandalized in Trois-Rivières, Que.",
      "triviality_score": 3
    },
    {
      "collected_at": "2026-06-17T20:09:44+09:00",
      "country": "JP",
      "country_ko": "일본",
      "id": "eb14d6830ddf",
      "image_url": "https://prcdn.freetls.fastly.net/release_image/5113/4066/5113-4066-da44900a4690365c88c904a16cc843ee-2048x1366.jpg?format=jpeg&auto=webp&fit=bounds&width=2400&height=1260",
      "lang_original": "ja",
      "lat": 43.0555,
      "lon": 141.3537,
      "processed_at": "2026-06-17T22:17:59+09:00",
      "raw_excerpt": "東急ホテルズ＆リゾーツ株式会社のプレスリリース（2026年4月15日 12時00分）すすきのに繰り出す前の「一杯」に。SAPPORO STREAM HOTELが提案する、旅人と地元の人が溶け合うハッピーアワーが5/7より開始。愛されスイーツの復刻プレートも展開！",
      "region": "Sapporo, Hokkaido",
      "source_name": "PR TIMES",
      "source_type": "google",
      "source_url": "https://prtimes.jp/main/html/rd/p/000004066.000005113.html",
      "summary_en": "SAPPORO STREAM HOTEL will start a happy hour on May 7 for guests and local people before they go out in Susukino. The hotel will also offer a plate with revived popular sweets.",
      "summary_ko": "삿포로 스트림 호텔이 5월 7일부터 스스키노로 나가기 전 여행객과 지역 주민이 함께 즐길 수 있는 해피아워를 시작한다. 호텔은 예전에 사랑받았던 디저트를 되살린 플레이드도 함께 선보인다.",
      "title_en": "Sapporo hotel starts a happy hour before nights out",
      "title_ko": "삿포로 호텔, 밤 외출 전 즐기는 해피아워 시작",
      "title_original": "すすきのに繰り出す前の「一杯」に。SAPPORO STREAM HOTELが提案する、旅人と地元の人が溶け合うハッピーアワーが5/7より開始。愛されスイーツの復刻プレートも展開！ | 東急ホテルズ＆リゾーツ株式会社のプレスリリース - PR TIMES",
      "triviality_score": 4
    },
    {
      "collected_at": "2026-06-17T12:03:42+09:00",
      "country": "AT",
      "country_ko": "오스트리아",
      "id": "43178d09c170",
      "image_url": "https://www.vienna.at/2026/05/Regions_KeyVisual_Sommer_Mitterbergblick_KeyVisual_Summer_View_Mitterberg16x9C_Zell_am_See-Kaprun.310634fd_original-vodl-10163669-16-9-1280x720.jpg?v=11cfa886",
      "lang_original": "de",
      "lat": 47.3235,
      "lon": 12.7968,
      "processed_at": "2026-06-17T16:10:26+09:00",
      "raw_excerpt": "Zell am See im Salzburger Pinzgau wurde vom US-Magazin „Travel + Leisure“ als eine der schönsten Kleinstädte Europas ausgezeichnet, wobei die beeindruckende natürliche Kulisse zwischen dem Zeller See und den Hohen Tauern hervorgehoben wird.",
      "region": "Salzburg Pinzgau",
      "source_name": "Vienna.at",
      "source_type": "google",
      "source_url": "https://www.vienna.at/das-ist-die-schoenste-kleinstadt-oesterreichs/10163669",
      "summary_en": "Zell am See in Salzburg's Pinzgau region was praised by Travel + Leisure as one of Europe's most beautiful small towns. The magazine highlighted its setting between Lake Zell and the Hohe Tauern mountains.",
      "summary_ko": "잘츠부르크 핀츠가우 지역의 첼암제가 Travel + Leisure가 꼽은 유럽의 아름다운 소도시 중 하나로 소개됐다. 이 매체는 첼러 호수와 호에 타우에른 산맥 사이에 자리한 자연 풍경을 높이 평가했다.",
      "title_en": "Zell am See Named Austria's Most Beautiful Small Town",
      "title_ko": "오스트리아의 아름다운 소도시로 뽑힌 첼암제",
      "title_original": "Das ist die schönste Kleinstadt Österreichs - Vienna.at",
      "triviality_score": 4
    },
    {
      "collected_at": "2026-06-18T04:14:12+09:00",
      "country": "JP",
      "country_ko": "일본",
      "id": "044b8686b797",
      "image_url": "https://cdn.image.st-hatena.com/image/scale/deb14dd34df7996f091ca40091358b7b9c55e5e2/backend=imagemagick;version=1;width=1300/https%3A%2F%2Fcdn-ak.f.st-hatena.com%2Fimages%2Ffotolife%2Fw%2Fweekendkanazawa%2F20230411%2F20230411175537.jpg",
      "lang_original": "ja",
      "lat": 36.5613,
      "lon": 136.6562,
      "processed_at": "2026-06-18T14:18:25+09:00",
      "raw_excerpt": "ハロウイン🎃やクリスマス🎄など、冬のイベントが迫ってきましたね！ケーキを食べる機会も増えるのでは？🍰 地元編集部厳選・金沢や金沢近郊のおすすめケーキ屋さんを紹介します！新店も追加しましたよ〜🌟チェックしてみて！",
      "region": "Ishikawa Prefecture",
      "source_name": "weekend-kanazawa.com",
      "source_type": "google",
      "source_url": "https://www.weekend-kanazawa.com/entry/kanazawa_cake",
      "summary_en": "A local Kanazawa team shares its favorite cake shops in Kanazawa and nearby areas. The guide covers cakes for special days and small treats, with some new shops added.",
      "summary_ko": "가나자와 현지 편집부가 가나자와와 주변 지역의 추천 케이크 가게를 소개했다. 특별한 날의 홀케이크부터 나를 위한 작은 간식까지 다루며, 새로 문을 연 가게도 추가됐다.",
      "title_en": "Local Editors Pick Cake Shops in Kanazawa, Hakusan, and Komatsu",
      "title_ko": "가나자와와 인근 지역의 추천 케이크 가게",
      "title_original": "【地元編集部厳選】金沢・白山・小松の絶品ケーキ屋さんまとめ。特別な日のホールケーキから自分へのご褒美まで - weekend-kanazawa.com",
      "triviality_score": 5
    },
    {
      "collected_at": "2026-06-17T14:06:14+09:00",
      "country": "IT",
      "country_ko": "이탈리아",
      "id": "cdd9fdd0fd30",
      "image_url": "https://www.ilrestodelcarlino.it/image-service/view/acePublic/alias/contentid/YjM4MzFhODMtOTNkYy00/0/il-tram-a-bologna-rivoluziona-la-viabilita-qui-siamo-in-zona-borgo-panigale-e-villaggio-ina.jpg?f=16:9&w=1200&h=675",
      "lang_original": "it",
      "lat": 44.522,
      "lon": 11.276,
      "processed_at": "2026-06-17T16:19:21+09:00",
      "raw_excerpt": "Bologna, 26 maggio 2026 – Eccola, la Guida galattica per autostoppisti a Bologna. Un vademecum che, come nel cele",
      "region": "Borgo Panigale, Bologna",
      "source_name": "Il Resto del Carlino",
      "source_type": "google",
      "source_url": "https://www.ilrestodelcarlino.it/bologna/cronaca/come-cambia-viabilita-borgo-panigale-tram-svi09jif-sck",
      "summary_en": "Bologna is preparing traffic changes in Borgo Panigale for tram work. The guide covers the route area from Villaggio Ina to Ducati.",
      "summary_ko": "볼로냐가 트램 공사를 위해 보르고 파니갈레의 교통 체계를 조정한다. 안내 내용은 빌라조 이나부터 두카티 주변까지의 이동 구간을 다룬다.",
      "title_en": "Traffic changes for Bologna tram work in Borgo Panigale",
      "title_ko": "볼로냐 트램 공사로 바뀌는 보르고 파니갈레 교통",
      "title_original": "Come cambia la viabilità a Borgo Panigale con il tram di Bologna: dal Villaggio Ina alla Ducati - Il Resto del Carlino",
      "triviality_score": 4
    },
    {
      "collected_at": "2026-06-18T04:07:59+09:00",
      "country": "AT",
      "country_ko": "오스트리아",
      "id": "5e2e69cf089a",
      "image_url": "https://www.sn.at/storage/image/6/2/3/8/1108326_als-herausforderungen-in-der-stadt-sieht-michael-strobl-im-bild-vorsitzende_metadaten_1FTRWC_mpusKe.jpg",
      "lang_original": "de",
      "lat": 47.8095,
      "lon": 13.055,
      "processed_at": "2026-06-18T12:26:22+09:00",
      "raw_excerpt": "In fünf Minuten sind alle wichtigen Orte des täglichen Bedarfs erreichbar. Das ist die Idee des Fünf-Minuten-Dorfs. Diese und weitere 49 Wohnlösungen präsentiert eine Ziviltechnikerkammer-Ausstellung. Für mehr Umsetzungen brauche es aber Anpassungen in den Fördersystemen, so die Experten.",
      "region": "Salzburg",
      "source_name": "Salzburger Nachrichten",
      "source_type": "google",
      "source_url": "https://www.sn.at/salzburg/chronik/ausstellung-zeigt-fuenf-minuten-dorf-statt-pflegeheim-man-koennte-es-einzelinitiativen-leichter-machen-art-645806",
      "summary_en": "An exhibition in Salzburg presents the idea of a five-minute village. It shows 50 housing solutions where daily needs can be reached within five minutes. Experts say funding rules need changes so small local projects can be easier to build.",
      "summary_ko": "잘츠부르크의 한 전시가 ‘5분 마을’ 구상을 소개한다. 생활에 필요한 주요 장소를 5분 안에 갈 수 있는 주거 해법 50가지를 보여 준다. 전문가들은 이런 작은 지역 프로젝트가 더 쉽게 실현되려면 지원 제도 개선이 필요하다고 말한다.",
      "title_en": "Exhibition Shows a Five-Minute Village Idea",
      "title_ko": "잘 사는 동네를 보여 주는 ‘5분 마을’ 전시",
      "title_original": "Ausstellung zeigt Fünf-Minuten-Dorf statt Pflegeheim: \"Man könnte es Einzelinitiativen leichter machen\" - Salzburger Nachrichten",
      "triviality_score": 4
    },
    {
      "collected_at": "2026-06-17T14:07:37+09:00",
      "country": "DE",
      "country_ko": "독일",
      "id": "87e06e03d8c3",
      "image_url": "https://images.mgpd.de/img/113843710/crop/c16_9-w1200/1346256218/1002338981/sta37943.jpg",
      "lang_original": "de",
      "lat": 48.241,
      "lon": 10.363,
      "processed_at": "2026-06-17T16:24:26+09:00",
      "raw_excerpt": "Im Mittelschwäbischen Heimatmuseum Krumbach erwartet Besucherinnen und Besucher eine große Lego-Ausstellung mit beeindruckenden Bauwerken und Mitmachaktionen.",
      "region": "Krumbach, Bavaria",
      "source_name": "Augsburger Allgemeine",
      "source_type": "google",
      "source_url": "https://www.augsburger-allgemeine.de/krumbach/krumbach-lego-ausstellung-bunte-steine-im-heimatmuseum-am-2-und-3-mai-114118183",
      "summary_en": "The Mittelschwäbisches Heimatmuseum in Krumbach will host a large Lego exhibition. Visitors can see impressive builds and join hands-on activities during the weekend.",
      "summary_ko": "독일 크룸바흐의 미텔슈베비셰스 향토박물관에서 대규모 레고 전시가 열린다. 방문객들은 인상적인 레고 작품을 보고 직접 참여하는 활동도 즐길 수 있다.",
      "title_en": "Lego Show Comes to Krumbach Museum",
      "title_ko": "크룸바흐 박물관에 레고 전시가 열린다",
      "title_original": "„Bunte Steine“ in Krumbach: Lego-Ausstellung lockt am Wochenende ins Mittelschwäbische Heimatmuseum - Augsburger Allgemeine",
      "triviality_score": 5
    },
    {
      "collected_at": "2026-06-17T12:03:40+09:00",
      "country": "CH",
      "country_ko": "스위스",
      "id": "e27a8f732af8",
      "image_url": "https://img-msp-prod.nzz.ch/2026/06/09/4bf922d5-9e1f-4d6d-b471-962f574014ee.jpg?width=1200&height=675&fit=bounds&quality=75&auto=webp&crop=9504,5346,x0,y231&wmark=nzz",
      "lang_original": "de",
      "lat": 47.4582,
      "lon": 8.5555,
      "processed_at": "2026-06-17T16:10:09+09:00",
      "raw_excerpt": "Die Agglomeration um den Flughafen will selbstbewusster auftreten, als urbaner Raum der Zukunft. Und dabei nicht zu sehr nach Zürich schielen, weil sie andere Stärken hat.",
      "region": "Zurich Airport region",
      "source_name": "Neue Zürcher Zeitung",
      "source_type": "google",
      "source_url": "https://www.nzz.ch/zuerich/mehr-als-ein-marketing-gag-was-es-mit-new-zurich-wirklich-auf-sich-hat-ld.10008085",
      "summary_en": "The area around Zurich Airport wants to present itself with more confidence. It says it can be a future urban area without copying Zurich, because it has its own strengths.",
      "summary_ko": "취리히 공항 주변 지역이 더 자신감 있는 모습으로 나서려 하고 있다. 이곳은 취리히를 그대로 따라 하기보다, 자신만의 강점을 가진 미래형 도시 공간이 될 수 있다고 말한다.",
      "title_en": "Airport Area Tries the Name New Zurich",
      "title_ko": "공항 주변 지역, ‘뉴 취리히’ 이름을 내세우다",
      "title_original": "«New Zurich» – mehr als bloss ein Marketing-Gag? - Neue Zürcher Zeitung",
      "triviality_score": 4
    },
    {
      "collected_at": "2026-06-17T09:17:18+09:00",
      "country": "CA",
      "country_ko": "캐나다",
      "id": "f96bfdc08af6",
      "image_url": "https://bloximages.chicago2.vip.townnews.com/durhamregion.com/content/tncms/assets/v3/editorial/9/07/907a7208-d05f-5313-a5c2-94686cd68a07/6a2b0603b627c.image.jpg?crop=1920%2C1008%2C0%2C35&resize=1200%2C630&order=crop%2Cresize",
      "lang_original": "en",
      "lat": 43.683,
      "lon": -80.43,
      "processed_at": "2026-06-17T15:52:29+09:00",
      "raw_excerpt": "A famous swimming hole in a breathtaking Ontario village is officially ready to welcome in adventurers for the summer. Here’s what to know about the 2026 season at the Elora Quarry.",
      "region": "Ontario",
      "source_name": "DurhamRegion.com",
      "source_type": "google",
      "source_url": "https://www.durhamregion.com/things-to-do/travel/elora-quarry-ontario-most-beautiful-village-2026/article_ef6bcc0f-9572-501d-8da7-9b6290cb989e.html",
      "summary_en": "Elora Quarry in Ontario is getting ready to welcome summer visitors. The famous limestone swimming hole sits in the village of Elora and has 12-metre-high cliffs.",
      "summary_ko": "온타리오의 엘로라 채석장이 여름 방문객을 맞을 준비를 하고 있습니다. 12미터 높이의 석회암 절벽으로 유명한 이 수영 명소는 엘로라 마을에 있습니다.",
      "title_en": "Elora Quarry opens for summer swimming",
      "title_ko": "엘로라 채석장, 여름 수영장 개장 준비",
      "title_original": "This picturesque 12-metre-high limestone swimming hole is about to open in Ontario’s most beautiful village - DurhamRegion.com",
      "triviality_score": 5
    },
    {
      "collected_at": "2026-06-17T18:03:41+09:00",
      "country": "IN",
      "country_ko": "인도",
      "id": "a0d048c9a9e5",
      "image_url": "https://th-i.thgim.com/public/incoming/1p8cpp/article71112707.ece/alternates/LANDSCAPE_1200/iStock-896114422.jpg",
      "lang_original": "en",
      "lat": 13.0827,
      "lon": 80.2707,
      "processed_at": "2026-06-17T18:20:56+09:00",
      "raw_excerpt": "Chennai Metrowater vows permanent piped water supply for Thiru.Vi.Ka Nagar residents after decades of reliance on tankers.",
      "region": "Chennai, Tamil Nadu",
      "source_name": "The Hindu National",
      "source_type": "rss",
      "source_url": "https://www.thehindu.com/news/cities/chennai/chennai-metrowater-promises-permanent-piped-water-supply-to-thiruvika-nagar-residents/article71097809.ece",
      "summary_en": "Chennai Metrowater says Thiru.Vi.Ka Nagar residents will get a permanent piped water supply. The area has depended on water tankers for decades.",
      "summary_ko": "첸나이 수도 당국은 티루비카 나가르 주민들에게 영구적인 상수도관 물 공급을 하겠다고 밝혔다. 이 지역은 수십 년 동안 급수차에 의존해 왔다.",
      "title_en": "Chennai Area Promised Piped Water After Years of Tankers",
      "title_ko": "첸나이 티루비카 나가르에 상수도 공급 약속",
      "title_original": "Chennai Metrowater promises permanent piped water supply to Thiru.Vi.Ka Nagar residents",
      "triviality_score": 4
    },
    {
      "collected_at": "2026-06-17T07:28:06+09:00",
      "country": "JP",
      "country_ko": "일본",
      "id": "e62a035e4d6e",
      "image_url": "https://media.japantoday.com/img/store/b7/00/6b373ad1996a32fb26a805fd05c4143cb056/2026-06-11t000000z_565308388_mt1nurpho00003mnvo_rtrmadp_3_saikazaki-coast-daily-life/_w1700.jpeg",
      "lang_original": "en",
      "lat": 34.19,
      "lon": 135.14,
      "processed_at": "2026-06-17T15:36:31+09:00",
      "raw_excerpt": "A large school of fish swarms near the surface of the water beneath an angler's fishing line at Saikazaki harbor in Wakayama City, Wakayama Prefecture. The coastal waters surrounding the port are known for a rich marine ecosystem that supports both local recreational angling and a thriving commercial fisheries industry,…",
      "region": "Wakayama Prefecture",
      "source_name": "Japan Today",
      "source_type": "rss",
      "source_url": "https://japantoday.com/category/picture-of-the-day/swarm-of-fish",
      "summary_en": "A large school of fish gathered near the water surface at Saikazaki harbor in Wakayama City. The port area is known for rich sea life that supports local anglers and commercial fishing.",
      "summary_ko": "와카야마시 사이카자키항에서 큰 물고기 떼가 수면 가까이 모였습니다. 이 항구 주변 바다는 해양 생태계가 풍부해 낚시객과 상업 어업을 함께 뒷받침합니다.",
      "title_en": "Fish Swarm at Saikazaki Harbor",
      "title_ko": "사이카자키항에 몰린 물고기 떼",
      "title_original": "Swarm of fish",
      "triviality_score": 5
    },
    {
      "collected_at": "2026-06-18T00:11:05+09:00",
      "country": "FR",
      "country_ko": "프랑스",
      "id": "17c4065b9dd4",
      "image_url": "https://cdn-s-www.ledauphine.com/images/791144CE-D854-4E7F-B6B2-F6BEC13D386F/FB1200/photo-1778487257.jpg",
      "lang_original": "fr",
      "lat": null,
      "lon": null,
      "processed_at": "2026-06-18T08:22:28+09:00",
      "raw_excerpt": "Au cœur du triangle Lyon, Grenoble, Chambéry, cette petite ville du Nord-Isère profite de son positionnement géographique pour attirer une ...",
      "region": "Nord-Isere, Auvergne-Rhone-Alpes",
      "source_name": "Le Dauphiné Libéré",
      "source_type": "google",
      "source_url": "https://www.ledauphine.com/magazine-immobilier/2026/05/13/quelle-est-cette-petite-ville-attirante-au-coeur-du-triangle-lyon-grenoble-chambery",
      "summary_en": "A small town in North Isere is gaining attention because of its location. It sits near Lyon, Grenoble, and Chambery, which helps it attract people interested in real estate.",
      "summary_ko": "북이제르의 한 작은 도시가 지리적 위치 덕분에 주목받고 있습니다. 이 도시는 리옹, 그르노블, 샹베리 사이에 있어 부동산을 찾는 사람들의 관심을 끌고 있습니다.",
      "title_en": "Small North Isere Town Attracts Home Buyers",
      "title_ko": "북이제르의 작은 도시, 집 찾는 사람들의 관심을 끌다",
      "title_original": "Immobilier. Quelle est cette petite ville attirante au cœur du triangle Lyon, Grenoble, Chambéry ? - Le Dauphiné Libéré",
      "triviality_score": 4
    },
    {
      "collected_at": "2026-06-18T08:01:36+09:00",
      "country": "CA",
      "country_ko": "캐나다",
      "id": "ad8cc53d6377",
      "image_url": "https://dam.mediacorp.sg/image/upload/s--65TPMtER--/c_fill,g_auto,h_676,w_1200/fl_relative,g_south_east,l_mediacorp:cna:watermark:2024-04:reuters_1,w_0.1/f_auto,q_auto/v1/one-cms/core/2026-06-17T225154Z_2_LYNXMPEM5G1W3_RTROPTP_3_SOCCER-WORLDCUP-GHA-PAN-FANS.JPG?itok=YRb3tilf",
      "lang_original": "en",
      "lat": 43.6332,
      "lon": -79.4186,
      "processed_at": "2026-06-19T13:00:18+09:00",
      "raw_excerpt": "TORONTO, June 17 : Boisterous fans of Ghana and Panama marched to Toronto Stadium to root for their teams in the World Cup Group L clash wearing traditional dress and waving flags, determined not to let high ticket prices and gloomy weather dampen their spirits.Wearing an ornate headdress made of beads and f",
      "region": "Toronto, Ontario",
      "source_name": "CNA Singapore",
      "source_type": "rss",
      "source_url": "https://www.channelnewsasia.com/sport/ghana-panama-fans-throng-toronto-streets-ahead-world-cup-clash-6191611",
      "summary_en": "Fans of Ghana and Panama marched to Toronto Stadium before their World Cup match. They wore traditional dress, waved flags, and kept cheering despite high ticket prices and gloomy weather.",
      "summary_ko": "가나와 파나마 팬들이 월드컵 경기를 앞두고 토론토 스타디움으로 행진했다. 팬들은 전통 의상을 입고 깃발을 흔들며, 비싼 티켓값과 흐린 날씨에도 응원을 이어 갔다.",
      "title_en": "Ghana and Panama Fans Fill Toronto Streets",
      "title_ko": "가나와 파나마 팬들, 토론토 거리를 채우다",
      "title_original": "Ghana, Panama fans throng Toronto streets ahead of World Cup clash",
      "triviality_score": 4
    },
    {
      "collected_at": "2026-06-17T20:11:46+09:00",
      "country": "MX",
      "country_ko": "멕시코",
      "id": "720a84308edf",
      "image_url": "https://yucatantoday.com/hubfs/Imported_Blog_Media/Convento-San-Antonio-de-Padua-Izamal-by-Nora-Garrett-Dec-02-2023-10-09-37-7463-PM.jpg",
      "lang_original": "es",
      "lat": 20.7099,
      "lon": -89.0943,
      "processed_at": "2026-06-18T00:14:31+09:00",
      "raw_excerpt": "Yucatán es tierra de fiestas, ferias y festivales. Amamos la pachanga. No importa el mes en que vengas, habrá fiestas en Yucatán.",
      "region": "Yucatán",
      "source_name": "Yucatán Today",
      "source_type": "google",
      "source_url": "https://yucatantoday.com/blog/calendario-de-ferias-y-fiestas-en-yucatan",
      "summary_en": "Yucatan has many local fairs, parties, and festivals. The article says visitors can find a celebration in almost any month.",
      "summary_ko": "유카탄에는 지역 박람회와 축제, 잔치가 많습니다. 이 글은 어느 달에 방문해도 거의 늘 즐길 만한 행사가 있다고 소개합니다.",
      "title_en": "Fairs and Festivals in Yucatan",
      "title_ko": "유카탄의 박람회와 축제 일정",
      "title_original": "Calendario de ferias y fiestas en Yucatán - Yucatán Today",
      "triviality_score": 4
    },
    {
      "collected_at": "2026-06-17T22:05:51+09:00",
      "country": "US",
      "country_ko": "미국",
      "id": "72f2b30d2453",
      "image_url": "https://www.worldatlas.com/r/w1200-q80/upload/8d/24/ea/shutterstock-1307627305-s3cdn.jpg",
      "lang_original": "en",
      "lat": 44.4759,
      "lon": -73.2121,
      "processed_at": "2026-06-18T00:20:20+09:00",
      "raw_excerpt": "Stop by for the weekend during one of their popular annual festivals and find out why Burlington is the friendliest small town in Vermont.",
      "region": "Burlington, Vermont",
      "source_name": "WorldAtlas",
      "source_type": "google",
      "source_url": "https://www.worldatlas.com/cities/this-is-the-friendliest-small-town-in-vermont-s59y26.html",
      "summary_en": "WorldAtlas says Burlington is the friendliest small town in Vermont. The article suggests visiting during one of its popular yearly festivals to see its welcoming local feel.",
      "summary_ko": "WorldAtlas는 벌링턴을 버몬트에서 가장 친절한 작은 마을로 소개했다. 인기 있는 연례 축제가 열리는 주말에 방문하면 이곳의 따뜻한 지역 분위기를 느낄 수 있다고 전했다.",
      "title_en": "Burlington Is Called Vermont's Friendliest Small Town",
      "title_ko": "버몬트에서 가장 친절한 작은 마을로 꼽힌 벌링턴",
      "title_original": "This Is The Friendliest Small Town In Vermont - WorldAtlas",
      "triviality_score": 4
    },
    {
      "collected_at": "2026-06-17T14:06:45+09:00",
      "country": "IT",
      "country_ko": "이탈리아",
      "id": "c6afcbb7f2d0",
      "image_url": "https://www.today.it/~media/horizontal-hi/26126926601872/gomm.jpg",
      "lang_original": "it",
      "lat": 44.4949,
      "lon": 11.3426,
      "processed_at": "2026-06-17T16:20:28+09:00",
      "raw_excerpt": "Piscine panoramiche, scivoli incastonati nel verde, aree benessere e attività outdoor: riparte la stagione estiva al Villaggio della Salute Più.",
      "region": "Bologna, Emilia-Romagna",
      "source_name": "today.it",
      "source_type": "google",
      "source_url": "https://www.today.it/speciale/riapre-villaggio-salute-bologna.html",
      "summary_en": "The summer season has started again at Villaggio della Salute Più. The park has scenic pools, slides set in greenery, wellness areas, and outdoor activities.",
      "summary_ko": "Villaggio della Salute Più가 여름 시즌을 맞아 다시 운영을 시작했다. 이곳에서는 전망 좋은 수영장, 초록 풍경 속 미끄럼틀, 웰니스 공간과 야외 활동을 즐길 수 있다.",
      "title_en": "Water Park Reopens in the Bologna Hills",
      "title_ko": "볼로냐 언덕 속 워터파크가 다시 문을 연다",
      "title_original": "Riapre l'Acquapark immerso tra le colline bolognesi - today.it",
      "triviality_score": 4
    },
    {
      "collected_at": "2026-06-17T20:10:20+09:00",
      "country": "NL",
      "country_ko": "네덜란드",
      "id": "fc15260d5ae6",
      "image_url": "https://dub.uu.nl/sites/default/files/styles/large/public/media/images/pexels-roman-odintsov-6798403%20%281%29.jpg?itok=rYl_4KsL",
      "lang_original": "en",
      "lat": 52.0907,
      "lon": 5.1214,
      "processed_at": "2026-06-17T22:19:38+09:00",
      "raw_excerpt": "Love is in the air! If you're looking for something special to do with your significant other this Valentine's Day, look no further. Hana Noshie has got some tips for you.",
      "region": "Utrecht",
      "source_name": "dub.uu.nl",
      "source_type": "google",
      "source_url": "https://dub.uu.nl/en/blog/what-do-utrecht-valentines-day",
      "summary_en": "A local Utrecht article shares ideas for couples on Valentine's Day. Hana Noshie gives tips for people looking for something special to do together.",
      "summary_ko": "위트레흐트에서 밸런타인데이에 연인과 함께할 만한 아이디어를 소개한 지역 글입니다. 하나 노시가 특별한 시간을 보내고 싶은 사람들을 위해 몇 가지 팁을 전합니다.",
      "title_en": "Valentine's Day Ideas in Utrecht",
      "title_ko": "위트레흐트 밸런타인데이 데이트 추천",
      "title_original": "What to do in Utrecht this Valentine's Day - dub.uu.nl",
      "triviality_score": 4
    }
  ]
}
