{
  "version": 2,
  "built_at": "2026-07-15T18:24:41+09:00",
  "page": 146,
  "page_size": 20,
  "count": 11,
  "items": [
    {
      "collected_at": "2026-07-15T16:03:32+09:00",
      "country": "MX",
      "country_ko": "멕시코",
      "fallback_reason": "",
      "id": "4c90133b00fa",
      "image_url": "https://oaxaca.eluniversal.com.mx/resizer/v2/SGXW2A3W3FDT7CWVWTGI5UU4FI.jpg?auth=29a318d2635e464a857ed09edc481ae381f33ba19115931e332bf0594359d64a",
      "lang_original": "es",
      "lat": 17.28,
      "lon": -96.55,
      "processed_at": "2026-07-15T16:22:51+09:00",
      "provider_used": "opencode",
      "raw_excerpt": "El evento que reúne la belleza y esplendor de los pueblos de la Sierra de Juárez en uno de los escenarios más imponentes de Oaxaca",
      "region": "Oaxaca",
      "source_name": "El Universal Oaxaca",
      "source_type": "google",
      "source_url": "https://oaxaca.eluniversal.com.mx/mas-de-oaxaca/guelaguetza-serrana-fechas-y-actividades-en-la-fiesta-de-calpulalpan-de-mendez/",
      "summary_en": "The Guelaguetza Serrana festival celebrates the beauty and culture of the Sierra de Juárez mountain villages. The event takes place in one of the most stunning settings in Oaxaca, Mexico. Activities and dates have been announced for this year's celebration in Calpulalpan de Méndez.",
      "summary_ko": "과라게트사 산악 축제는 시에라데후아레즈 산악 마을들의 아름다움과 문화를 기념합니다. 이 행사는 멕시코 오아하카 주에서 가장 장엄한 풍경 중 하나인 곳에서 열립니다. 칼풀알판 데 멘데스에서 올해 축제 일정과 행사 내용이 발표되었습니다.",
      "title_en": "Guelaguetza Serrana Festival Returns to Calpulalpan de Méndez, Oaxaca",
      "title_ko": "칼풀알판 데 멘데스에서 열리는 과라게트사 산악 축제",
      "title_original": "Guelaguetza Serrana. Fechas y actividades en la fiesta de Calpulalpan de Méndez - El Universal Oaxaca",
      "triviality_score": 5
    },
    {
      "collected_at": "2026-07-15T16:03:42+09:00",
      "country": "IN",
      "country_ko": "인도",
      "fallback_reason": "",
      "id": "5abeffba6d49",
      "image_url": "https://th-i.thgim.com/public/incoming/w4o5qu/article71222434.ece/alternates/LANDSCAPE_1200/Uterine%20Fibroid%201.jpeg",
      "lang_original": "en",
      "lat": 17.385,
      "lon": 78.4867,
      "processed_at": "2026-07-15T16:23:08+09:00",
      "provider_used": "opencode",
      "raw_excerpt": "Hyderabad doctors successfully treat a woman with a rare giant uterine fibroid, saving her life through emergency surgery.",
      "region": "Telangana",
      "source_name": "The Hindu National",
      "source_type": "rss",
      "source_url": "https://www.thehindu.com/news/cities/Hyderabad/hyderabad-doctors-save-woman-with-rare-giant-uterine-fibroid-complication/article71222432.ece",
      "summary_en": "Hyderabad doctors successfully treated a woman with a rare giant uterine fibroid. They performed emergency surgery to save her life.",
      "summary_ko": "히드라바드 의사들이 희귀 거대 자궁 근종을 앓던 여성을 성공적으로 치료했습니다. 이들은 응급 수술을 통해 환자의 생명을 구했습니다.",
      "title_en": "Hyderabad doctors save woman with rare giant uterine fibroid complication",
      "title_ko": "히드라바드 의사들, 희귀 거대 자궁 근종 합병증 환자 구해",
      "title_original": "Hyderabad doctors save woman with rare giant uterine fibroid complication",
      "triviality_score": 3
    },
    {
      "collected_at": "2026-07-15T16:03:42+09:00",
      "country": "SG",
      "country_ko": "싱가포르",
      "fallback_reason": "",
      "id": "b65c61698952",
      "image_url": "https://dam.mediacorp.sg/image/upload/s--wlHggpMS--/c_crop,h_561,w_999,x_1,y_53/c_fill,g_auto,h_676,w_1200/fl_relative,g_south_east,l_one-cms:core:watermark:ap_data-1,w_0.1/f_auto,q_auto/v1/one-cms/core/Film_Review_-_The_Odyssey_3523_.jpg?itok=n3WqjIQ7",
      "lang_original": "en",
      "lat": 1.3521,
      "lon": 103.8198,
      "processed_at": "2026-07-15T16:23:30+09:00",
      "provider_used": "opencode",
      "raw_excerpt": "Directed by award-winning filmmaker Christopher Nolan, The Odyssey is also the first movie to be shot entirely on IMAX's 70mm film cameras.",
      "region": null,
      "source_name": "CNA Singapore",
      "source_type": "rss",
      "source_url": "https://cnalifestyle.channelnewsasia.com/entertainment/odyssey-35mm-film-shaw-theatres-singapore-586001",
      "summary_en": "Shaw Theatres in Singapore will be the only cinema in Southeast Asia to show Christopher Nolan's The Odyssey on 35mm film. The film was shot using IMAX's 70mm film cameras. Movie fans can watch this special format at Shaw Theatres.",
      "summary_ko": "싱가포르의 쇼 시어터는 크리스토퍼 놀란 감독의 '디 오디세이'를 35mm 필름으로 상영하는 동남아시아 유일의 영화관입니다. 이 영화는 IMAX의 70mm 필름 카메라로 촬영되었습니다. 영화 팬들은 이곳에서 특별한 필름 포맷으로 영화를 즐길 수 있습니다.",
      "title_en": "Singapore cinema to screen The Odyssey on 35mm film",
      "title_ko": "싱가포르 쇼 시어터, '디 오디세이'를 35mm 필름으로 상영",
      "title_original": "Shaw Theatres in Singapore will screen The Odyssey on 35mm film, only cinema in Southeast Asia to do so",
      "triviality_score": 4
    },
    {
      "collected_at": "2026-07-15T16:04:16+09:00",
      "country": "AU",
      "country_ko": "호주",
      "fallback_reason": "",
      "id": "3bab9edb513b",
      "image_url": "https://live-production.wcms.abc-cdn.net.au/da868eef7a3f3aef3bbe62161deae781?impolicy=wcms_watermark_news&cropH=2592&cropW=4608&xPos=0&yPos=274&width=862&height=485&imformat=generic",
      "lang_original": "en",
      "lat": -12.4634,
      "lon": 130.8456,
      "processed_at": "2026-07-15T16:23:45+09:00",
      "provider_used": "opencode",
      "raw_excerpt": "A Darwin tobacconist has pleaded guilty to tax evasion after police busted him with more than 330 kilograms of tobacco labelled as Chinese tea and 110,000 illegally imported cigarettes.",
      "region": "Northern Territory",
      "source_name": "ABC Australia News",
      "source_type": "rss",
      "source_url": "https://www.abc.net.au/news/2026-07-15/darwin-illegal-tobacco-bust-nets-110000-cigarettes-guilty-plea/106918236",
      "summary_en": "A Darwin tobacco shop owner pleaded guilty to tax evasion. Police found 330 kilograms of tobacco labelled as Chinese tea. They also discovered 110,000 illegally imported cigarettes.",
      "summary_ko": "다윈의 한 담배 가게 주인이 탈세 혐의로 유죄를 인정했습니다. 경찰은 중국차로 표시된 담배 330kg과 불법 수입 담배 11만 개피를 적발했습니다.",
      "title_en": "Darwin Tobacconist Pleads Guilty to Tax Evasion with Hidden Tobacco",
      "title_ko": "다윈 담배상인, 탈세 혐의로 유죄 인정",
      "title_original": "Darwin man busted with 110,000 cigarettes, 330kg of tobacco pleads guilty",
      "triviality_score": 4
    },
    {
      "collected_at": "2026-07-15T18:01:52+09:00",
      "country": "NO",
      "country_ko": "노르웨이",
      "fallback_reason": "",
      "id": "5720cd7a285c",
      "image_url": "https://assets.thelocal.com/cdn-cgi/rs:fit:1200/quality:75/plain/https://apiwp.thelocal.com/wp-content/uploads/2024/07/watermarks-logo-Norway.word-of-the-day-ha-en-fin-ferie.jpg@webp",
      "lang_original": "en",
      "lat": 60.472,
      "lon": 8.4689,
      "processed_at": "2026-07-15T18:16:58+09:00",
      "provider_used": "opencode",
      "raw_excerpt": "In July, plenty of people you know in Norway will be heading off on their annual summer holiday. Today’s expression lets you wish them the best.",
      "region": null,
      "source_name": "The Local Norway",
      "source_type": "rss",
      "source_url": "https://www.thelocal.no/20240703/norwegian-expression-of-the-day-ha-en-fin-ferie",
      "summary_en": "Norwegians use 'Ha en fin ferie' to wish someone a good summer holiday. Many people in Norway take their annual vacation in July. This simple phrase is a friendly way to send warm wishes to travelers.",
      "summary_ko": "노르웨이 사람들은 'Ha en fin ferie'라는 말로 좋은 여름 휴가를 기원합니다. 7월이 되면 많은 노르웨이인들이 연례 휴가를 떠납니다. 이 간단한 표현은 여행하는 사람들에게 따뜻한 마음을 전하는 좋은 방법입니다.",
      "title_en": "Norwegian phrase of the day: Have a nice holiday",
      "title_ko": "오늘의 노르웨이어 표현: Ha en fin ferie",
      "title_original": "Norwegian expression of the day: Ha en fin ferie",
      "triviality_score": 4
    },
    {
      "collected_at": "2026-07-15T18:01:54+09:00",
      "country": "NL",
      "country_ko": "네덜란드",
      "fallback_reason": "",
      "id": "7c70de9ccb4a",
      "image_url": "https://www.dutchnews.nl/wpcms/wp-content/uploads/2026/07/Solvinity-.jpg",
      "lang_original": "en",
      "lat": 51.9225,
      "lon": 4.4792,
      "processed_at": "2026-07-15T18:17:12+09:00",
      "provider_used": "opencode",
      "raw_excerpt": "A Rotterdam judge has upheld a government ban on the acquisition of Dutch IT company Solvinity by American company Kyndryl, meaning the acquisition cannot go ahead for now. The American company announced its plans to acquire Solvinity last year, but junior minister for digital sovereignty Willemijn Aerdts blocked it in May, saying there’s a risk the US government could gain access to sensitive data via US legislation. Under its Cloud Act, US authorities can force American-owned companies to hand",
      "region": "Rotterdam",
      "source_name": "DutchNews.nl",
      "source_type": "rss",
      "source_url": "https://www.dutchnews.nl/2026/07/solvinity-acquisition-ban-upheld-by-rotterdam-judge/",
      "summary_en": "A judge in Rotterdam upheld a Dutch government ban on American company Kyndryl acquiring IT firm Solvinity. The government blocked the deal over concerns that US cloud laws could let American authorities access sensitive Dutch data. Solvinity provides IT services to Dutch hospitals, government agencies and businesses.",
      "summary_ko": "로테르담 법원은 미국 기업 킨드릴의 네덜란드 IT 기업 솔비니티 인수를 금지한 정부 결정을 유지했습니다. 미국 클라우드법에 따라 미 당국이 민감한 네덜란드 데이터에 접근할 수 있다는 우려가 인수 불허의 원인입니다. 솔비니티는 네덜란드 병원과 정부 기관에 IT 서비스를 제공하고 있습니다.",
      "title_en": "Dutch court blocks American tech company from buying Solvinity",
      "title_ko": "네덜란드 법원, 미국 기업의 솔비니티 인수 차단 유지",
      "title_original": "Solvinity acquisition ban upheld by Rotterdam judge",
      "triviality_score": 3
    },
    {
      "collected_at": "2026-07-15T18:01:55+09:00",
      "country": "FI",
      "country_ko": "핀란드",
      "fallback_reason": "",
      "id": "e2aee04deec4",
      "image_url": "https://img.img-cdn.yle.fi/crop_extract,w_6960,h_3915,x_0,y_485/crop_fill,w_1200,h_628/f_auto/39-16752236a53ba891c63a/1783872647",
      "lang_original": "en",
      "lat": null,
      "lon": null,
      "processed_at": "2026-07-15T18:17:54+09:00",
      "provider_used": "opencode",
      "raw_excerpt": "Forecasters say some areas could receive almost a month's worth of rain over the weekend.",
      "region": null,
      "source_name": "YLE News",
      "source_type": "rss",
      "source_url": "https://yle.fi/a/74-20236427",
      "summary_en": "Finland is staying cool compared to the rest of Europe. Heavy rain is expected over the weekend. Some areas might get almost a month's worth of rain.",
      "summary_ko": "핀란드는 유럽에서 가장 선선한 나라 중 하나로 남아 있습니다. 주말에 폭우가 예상됩니다. 일부 지역에는 한 달치 비가 내릴 수 있습니다.",
      "title_en": "Finland remains one of Europe's coolest countries as heavy rain looms",
      "title_ko": "핀란드, 유럽에서 가장 선선한 나라 유지... 폭우 예보",
      "title_original": "Finland remains one of Europe's coolest countries as heavy rain looms",
      "triviality_score": 4
    },
    {
      "collected_at": "2026-07-15T18:02:35+09:00",
      "country": "TR",
      "country_ko": "튀르키예",
      "fallback_reason": "",
      "id": "7536a6d396e0",
      "image_url": "https://assets.thelocal.com/cdn-cgi/rs:fit:1200/quality:75/plain/https://apiwp.thelocal.com/wp-content/uploads/2026/07/watermarks-logo-a001_NormalPreviewoops.jpg@webp",
      "lang_original": "en",
      "lat": 39.9334,
      "lon": 32.8597,
      "processed_at": "2026-07-15T18:18:44+09:00",
      "provider_used": "opencode",
      "raw_excerpt": "Sweden's government has confirmed media reports that government security adviser Niclas Kvarnström forgot a notebook at last week's Nato summit in Ankara.",
      "region": "Ankara",
      "source_name": "The Local Sweden",
      "source_type": "rss",
      "source_url": "https://www.thelocal.se/20260715/swedens-security-advisor-forgets-notebook-at-nato-summit",
      "summary_en": "Sweden's government confirmed that security adviser Niclas Kvarnström forgot a notebook at the NATO summit in Ankara, Turkey. The notebook was left behind at last week's meeting. The government acknowledged the incident after media reports.",
      "summary_ko": "스웨덴 정부는 안보 보좌관 니클라스 크바른스트룀이 터키 앙카라에서 열린 NATO 정상회의에서 노트북을 잊어버렸다고 확인했습니다. 지난주 회의에서 노트북을 두고 갔으며, 정부는 언론 보도 후 이 사건을 인정했습니다.",
      "title_en": "Sweden's security advisor forgets notebook at Nato summit",
      "title_ko": "스웨덴 안보 보좌관, NATO 정상회의에서 노트북 분실",
      "title_original": "Sweden's security advisor forgets notebook at Nato summit",
      "triviality_score": 4
    },
    {
      "collected_at": "2026-07-15T18:04:44+09:00",
      "country": "ES",
      "country_ko": "스페인",
      "fallback_reason": "",
      "id": "01206dfc558b",
      "image_url": "https://assets.thelocal.com/cdn-cgi/rs:fit:1200/quality:75/plain/https://apiwp.thelocal.com/wp-content/uploads/2026/07/watermarks-logo-AFP__20260713__C22T43A__v1__MidRes__SpainFireEmergency.jpg@webp",
      "lang_original": "en",
      "lat": null,
      "lon": null,
      "processed_at": "2026-07-15T18:23:05+09:00",
      "provider_used": "opencode",
      "raw_excerpt": "Twelve of the 13 victims of a deadly wildfire that swept through Andalusia in southern Spain were foreign nationals, the authorities said on Tuesday after completing post-mortem examinations.",
      "region": "Andalusia",
      "source_name": "The Local Spain",
      "source_type": "rss",
      "source_url": "https://www.thelocal.es/20260715/spain-confirms-12-foreigners-among-13-wildfire-victims",
      "summary_en": "Twelve of 13 victims from a deadly wildfire in Andalusia, southern Spain, were foreign nationals. British and American citizens were among those killed in the blaze.",
      "summary_ko": "남부 스페인 안달루시아地区的 치명적인 산불로 사망한 13명 중 12명은 외국인이었습니다. 영국인과 미국인 시민들이 포함되어 있었습니다.",
      "title_en": "Seven Brits and one American among 12 foreigners killed in Spain wildfire",
      "title_ko": "스페인 산불로 사망한 외국인 12명 중 영국인 7명과 미국인 1명 포함",
      "title_original": "Seven Brits and one American among 12 foreigners killed in Spain's wildfire",
      "triviality_score": 3
    },
    {
      "collected_at": "2026-07-15T18:04:45+09:00",
      "country": "JP",
      "country_ko": "일본",
      "fallback_reason": "",
      "id": "8e25d6b72205",
      "image_url": "https://media.japantoday.com/img/store/ec/02/01443fb1fa6e51eaa958a5a88ecb66125f84/screenshot-2026-07-15-at-8-43-58/_w1700.png",
      "lang_original": "en",
      "lat": 35.3606,
      "lon": 138.7274,
      "processed_at": "2026-07-15T18:23:31+09:00",
      "provider_used": "opencode",
      "raw_excerpt": "With June usually being a month of rainy, gloomy weather in Japan, you’ve really got to pack as much summer fun as you can into your July and August weekends. Sometimes that means doubling up on seasonal activities, like going to fireworks shows or shrine festivals on a Saturday and…",
      "region": null,
      "source_name": "Japan Today",
      "source_type": "rss",
      "source_url": "https://japantoday.com/category/national/hiker-needs-to-be-rescued-from-mount-fuji-two-times-in-two-days-but-system-is-working-as-intended",
      "summary_en": "A hiker was rescued from Mount Fuji two separate times in two days. The incident occurred during a period of typically rainy and gloomy weather in Japan. Officials noted that the rescue system is working as intended.",
      "summary_ko": "한 하이커가 2일 연속 후지산에서 두 차례 구조 요청을 해야 했습니다. 이번 사건은 일본에서 흔히 비가 오고 흐린 시기에 발생했습니다. 관계자들은 구조 시스템이 의도대로 작동하고 있다고 밝혔습니다.",
      "title_en": "Hiker rescued from Mount Fuji twice in two days",
      "title_ko": "하이커, 2일 연속 후지산에서 두 차례 구조",
      "title_original": "Hiker needs to be rescued from Mount Fuji two times in two days",
      "triviality_score": 4
    },
    {
      "collected_at": "2026-07-15T18:12:52+09:00",
      "country": "US",
      "country_ko": "미국",
      "fallback_reason": "",
      "id": "fb67101f9fb6",
      "image_url": "https://bdc2020.o0bc.com/wp-content/uploads/2026/03/20251111194455510492000000-o-69ab063073481-768x432.jpg",
      "lang_original": "en",
      "lat": 44.25,
      "lon": -69.8,
      "processed_at": "2026-07-15T18:24:25+09:00",
      "provider_used": "opencode",
      "raw_excerpt": "A nearly 40-acre, 21-building property in Pittston, Maine — an “antique village” known as Tut Hill — is once again on the market.",
      "region": "Maine",
      "source_name": "Boston.com",
      "source_type": "google",
      "source_url": "https://www.boston.com/real-estate/on-the-market/2026/03/06/you-can-be-the-proud-owner-of-an-entire-21-building-maine-village-its-kind-of-a-steal/",
      "summary_en": "A nearly 40-acre antique village called Tut Hill in Pittston, Maine is on the market. The property includes 21 buildings and is being called a steal.",
      "summary_ko": "메인주 피츠턴에 위치한 '터트 힐'이라는 이름의 약 40에이커 규모 고solete 마을이 매물로 나왔다. 이 부지에는 21개 건물이 들어서 있으며 가격이 매우 저렴하다는 평가를 받고 있다.",
      "title_en": "Entire 21-building Maine village for sale",
      "title_ko": "메인주 21개 건물 전체가 하나의 마을, 매물로 나와",
      "title_original": "You can be the proud owner of an entire 21-building Maine village. It’s kind of a steal. - Boston.com",
      "triviality_score": 5
    }
  ]
}
